{"generated_at": "2026-05-15T06:31:01.292623-05:00", "picks": [{"player": "Devin Vassell", "team": "SAS", "opp": "MIN", "stat": "PTS", "line": 7.5, "dir": "OVER", "tier": "GOBLIN", "p_cal": 0.874504451179164}, {"player": "Donovan Mitchell", "team": "CLE", "opp": "DET", "stat": "AST", "line": 3.5, "dir": "UNDER", "tier": "STANDARD", "p_cal": 0.7518553939313987}, {"player": "Isaiah Stewart", "team": "DET", "opp": "CLE", "stat": "REB", "line": 2.5, "dir": "OVER", "tier": "DEMON", "p_cal": 0.7675150638405466}, {"player": "Daniss Jenkins", "team": "DET", "opp": "CLE", "stat": "AST", "line": 1.5, "dir": "OVER", "tier": "GOBLIN", "p_cal": 0.8686464634512054}, {"player": "Devin Vassell", "team": "SAS", "opp": "MIN", "stat": "PTS", "line": 8.5, "dir": "OVER", "tier": "GOBLIN", "p_cal": 0.8649413192612592}, {"player": "Max Strus", "team": "CLE", "opp": "DET", "stat": "REB", "line": 2.5, "dir": "OVER", "tier": "GOBLIN", "p_cal": 0.8600151810348623}, {"player": "Jalen Duren", "team": "DET", "opp": "CLE", "stat": "AST", "line": 0.5, "dir": "OVER", "tier": "GOBLIN", "p_cal": 0.8551163521914196}, {"player": "Dylan Harper", "team": "SAS", "opp": "MIN", "stat": "PTS", "line": 7.5, "dir": "OVER", "tier": "GOBLIN", "p_cal": 0.8545614939959518}, {"player": "Naz Reid", "team": "MIN", "opp": "SAS", "stat": "PRA", "line": 18.5, "dir": "OVER", "tier": "GOBLIN", "p_cal": 0.8531094694238375}, {"player": "Tobias Harris", "team": "DET", "opp": "CLE", "stat": "PR", "line": 19.5, "dir": "OVER", "tier": "GOBLIN", "p_cal": 0.8507714891470362}, {"player": "Ausar Thompson", "team": "DET", "opp": "CLE", "stat": "AST", "line": 1.5, "dir": "OVER", "tier": "GOBLIN", "p_cal": 0.8504127133847968}, {"player": "Dylan Harper", "team": "SAS", "opp": "MIN", "stat": "PTS", "line": 6.5, "dir": "OVER", "tier": "GOBLIN", "p_cal": 0.8485131699967848}, {"player": "Devin Vassell", "team": "SAS", "opp": "MIN", "stat": "PTS", "line": 9.5, "dir": "OVER", "tier": "GOBLIN", "p_cal": 0.8465799308084607}, {"player": "Max Strus", "team": "CLE", "opp": "DET", "stat": "REB", "line": 3.5, "dir": "OVER", "tier": "GOBLIN", "p_cal": 0.8460565696514613}, {"player": "De'Aaron Fox", "team": "SAS", "opp": "MIN", "stat": "PTS", "line": 11.5, "dir": "OVER", "tier": "GOBLIN", "p_cal": 0.8456998564859001}, {"player": "Tobias Harris", "team": "DET", "opp": "CLE", "stat": "PRA", "line": 22.5, "dir": "OVER", "tier": "GOBLIN", "p_cal": 0.8451202167700336}, {"player": "Tobias Harris", "team": "DET", "opp": "CLE", "stat": "PR", "line": 20.5, "dir": "OVER", "tier": "GOBLIN", "p_cal": 0.8441031367074882}, {"player": "Tobias Harris", "team": "DET", "opp": "CLE", "stat": "PTS", "line": 14.5, "dir": "OVER", "tier": "GOBLIN", "p_cal": 0.8438690778091387}, {"player": "Daniss Jenkins", "team": "DET", "opp": "CLE", "stat": "RA", "line": 3.5, "dir": "OVER", "tier": "GOBLIN", "p_cal": 0.8427455750796743}, {"player": "Naz Reid", "team": "MIN", "opp": "SAS", "stat": "PTS", "line": 7.5, "dir": "OVER", "tier": "GOBLIN", "p_cal": 0.842028853859743}, {"player": "Tobias Harris", "team": "DET", "opp": "CLE", "stat": "REB", "line": 4.5, "dir": "OVER", "tier": "GOBLIN", "p_cal": 0.8414897684342058}, {"player": "Tobias Harris", "team": "DET", "opp": "CLE", "stat": "REB", "line": 5.5, "dir": "OVER", "tier": "GOBLIN", "p_cal": 0.8409010614356737}, {"player": "Evan Mobley", "team": "CLE", "opp": "DET", "stat": "AST", "line": 2.5, "dir": "OVER", "tier": "GOBLIN", "p_cal": 0.8406529468110808}, {"player": "Julian Champagnie", "team": "SAS", "opp": "MIN", "stat": "PTS", "line": 4.5, "dir": "OVER", "tier": "GOBLIN", "p_cal": 0.8389319730248348}, {"player": "Julian Champagnie", "team": "SAS", "opp": "MIN", "stat": "PRA", "line": 11.5, "dir": "OVER", "tier": "GOBLIN", "p_cal": 0.838417065097783}, {"player": "De'Aaron Fox", "team": "SAS", "opp": "MIN", "stat": "PR", "line": 14.5, "dir": "OVER", "tier": "GOBLIN", "p_cal": 0.8381487415720285}, {"player": "Dennis Schr\u00f6der", "team": "CLE", "opp": "DET", "stat": "PTS", "line": 2.5, "dir": "OVER", "tier": "GOBLIN", "p_cal": 0.8375613091923109}, {"player": "Cade Cunningham", "team": "DET", "opp": "CLE", "stat": "FG3M", "line": 1.5, "dir": "OVER", "tier": "GOBLIN", "p_cal": 0.8375487616315755}, {"player": "Max Strus", "team": "CLE", "opp": "DET", "stat": "RA", "line": 4.5, "dir": "OVER", "tier": "GOBLIN", "p_cal": 0.8374551009966058}, {"player": "Tobias Harris", "team": "DET", "opp": "CLE", "stat": "PA", "line": 16.5, "dir": "OVER", "tier": "GOBLIN", "p_cal": 0.8365282572268018}, {"player": "De'Aaron Fox", "team": "SAS", "opp": "MIN", "stat": "PR", "line": 16.5, "dir": "OVER", "tier": "GOBLIN", "p_cal": 0.8348155279704409}, {"player": "Naz Reid", "team": "MIN", "opp": "SAS", "stat": "PRA", "line": 19.5, "dir": "OVER", "tier": "GOBLIN", "p_cal": 0.8346220003032476}, {"player": "Julian Champagnie", "team": "SAS", "opp": "MIN", "stat": "PR", "line": 9.5, "dir": "OVER", "tier": "GOBLIN", "p_cal": 0.8342779415577811}, {"player": "Cade Cunningham", "team": "DET", "opp": "CLE", "stat": "PTS", "line": 22.5, "dir": "OVER", "tier": "GOBLIN", "p_cal": 0.8338644535418835}, {"player": "De'Aaron Fox", "team": "SAS", "opp": "MIN", "stat": "PTS", "line": 12.5, "dir": "OVER", "tier": "GOBLIN", "p_cal": 0.8325713192660412}, {"player": "Julian Champagnie", "team": "SAS", "opp": "MIN", "stat": "PTS", "line": 5.5, "dir": "OVER", "tier": "GOBLIN", "p_cal": 0.8319896957615446}, {"player": "Dean Wade", "team": "CLE", "opp": "DET", "stat": "PTS", "line": 0.5, "dir": "OVER", "tier": "GOBLIN", "p_cal": 0.8315296851359437}, {"player": "Julian Champagnie", "team": "SAS", "opp": "MIN", "stat": "PR", "line": 10.5, "dir": "OVER", "tier": "GOBLIN", "p_cal": 0.8311165549421189}, {"player": "Naz Reid", "team": "MIN", "opp": "SAS", "stat": "PRA", "line": 17.5, "dir": "OVER", "tier": "GOBLIN", "p_cal": 0.8308814059611634}, {"player": "Dylan Harper", "team": "SAS", "opp": "MIN", "stat": "PR", "line": 10.5, "dir": "OVER", "tier": "GOBLIN", "p_cal": 0.8306810142102846}, {"player": "Cade Cunningham", "team": "DET", "opp": "CLE", "stat": "PA", "line": 29.5, "dir": "OVER", "tier": "GOBLIN", "p_cal": 0.8300540203986786}, {"player": "Max Strus", "team": "CLE", "opp": "DET", "stat": "PR", "line": 8.5, "dir": "OVER", "tier": "GOBLIN", "p_cal": 0.8278689532678393}, {"player": "Dylan Harper", "team": "SAS", "opp": "MIN", "stat": "PR", "line": 11.5, "dir": "OVER", "tier": "GOBLIN", "p_cal": 0.8274926678239551}, {"player": "Dylan Harper", "team": "SAS", "opp": "MIN", "stat": "PR", "line": 9.5, "dir": "OVER", "tier": "GOBLIN", "p_cal": 0.8260358893979391}, {"player": "Naz Reid", "team": "MIN", "opp": "SAS", "stat": "RA", "line": 7.5, "dir": "OVER", "tier": "GOBLIN", "p_cal": 0.825472497855801}, {"player": "De'Aaron Fox", "team": "SAS", "opp": "MIN", "stat": "PTS", "line": 13.5, "dir": "OVER", "tier": "GOBLIN", "p_cal": 0.8250439581921207}, {"player": "Rudy Gobert", "team": "MIN", "opp": "SAS", "stat": "AST", "line": 0.5, "dir": "OVER", "tier": "GOBLIN", "p_cal": 0.8243367918452473}, {"player": "Julian Champagnie", "team": "SAS", "opp": "MIN", "stat": "PA", "line": 6.5, "dir": "OVER", "tier": "GOBLIN", "p_cal": 0.8241601015101631}, {"player": "Devin Vassell", "team": "SAS", "opp": "MIN", "stat": "PRA", "line": 14.5, "dir": "OVER", "tier": "GOBLIN", "p_cal": 0.8241183844919054}, {"player": "Evan Mobley", "team": "CLE", "opp": "DET", "stat": "PA", "line": 13.5, "dir": "OVER", "tier": "GOBLIN", "p_cal": 0.8239328435939216}], "total_legs": 1678, "total_slips": 6}