{
  "generated_at_utc": "2026-05-10T18:25:23Z",
  "slips": [
    {
      "label": "5-leg",
      "legs": [
        {
          "player": "Ausar Thompson",
          "tier": "GOBLIN",
          "projection_id": "11862487|Ausar Thompson|AST|GOBLIN|2.5|OVER",
          "source_projection_id": 11862487,
          "game_id": 156892,
          "game_date": "2026-05-05",
          "home": 1,
          "opp": "CLE",
          "player_key": "ausar thompson",
          "team": "DET",
          "stat": "AST",
          "stat_raw": "ASSISTS",
          "stat_is_canonical": 1,
          "line": 2.5,
          "direction": "OVER",
          "more_allowed": 1,
          "less_allowed": 0,
          "main_line": NaN,
          "alt_line": NaN,
          "is_main": 0,
          "odds_type": "goblin",
          "start_time": "2026-05-05T19:00:00.000-04:00",
          "updated_at": "2026-05-05 12:07:49.396000+00:00",
          "spread": -3.5,
          "home_team": "DET",
          "away_team": "CLE",
          "home_spread": -3.5,
          "away_spread": 3.5,
          "game_spread": -3.5,
          "spread_source": "rotowire",
          "spread_ok": true,
          "spread_reason": "ok",
          "minutes_s": 0.7,
          "p": 0.692080791920808,
          "p_role": 0.6976802319768023,
          "p_adj": 0.7268193792441978,
          "p_close": 0.7096790320967903,
          "p_close_raw": 0.7025797420257974,
          "p_close_role": 0.7096790320967903,
          "q_blowout": 0.13550088939970018,
          "q_blowout_spread_only": 0.26070104207215794,
          "q_blowout_team_adj": -0.007070125862806323,
          "q_blowout_matchup_adj": -0.11813002680965147,
          "blowout_minute_drop_base": 4.70922281080221,
          "blowout_minute_drop": 4.70922281080221,
          "blowout_rule_minute_drop_mult": 1.0,
          "blowout_rule_sensitivity_mult": 1.0,
          "blowout_rule_count": 0,
          "blowout_rules_applied": "",
          "minutes_s_blowout": 0.5319999999999999,
          "under_blowout_sens_mult": 0.76,
          "under_blowout_sens_eligible": false,
          "minutes_s_close": 0.24499999999999997,
          "is_star": false,
          "rotation_tier": "starter",
          "blowout_minute_delta": -4.70922281080221,
          "blowout_base_min_for_curve": 31.104367181436462,
          "fragility": 0.01690736174709404,
          "fragility_abs": 0.011998800119987996,
          "fragility_gap_core": 0.011998800119987996,
          "fragility_gap_usage": 0.011998800119987996,
          "fragility_gap_dir": 0.011998800119987996,
          "usage_dep": 0.883476,
          "usage_dep_capped": 0.883476,
          "usage_dep_cap": 1.04,
          "usage_dep_eff": 1.0,
          "usage_risk_gate": 0.0,
          "usage_baseline": 0.92,
          "usage_producer_mult": 0.99,
          "usage_pressure_mult": 0.97,
          "usage_usg_pct": NaN,
          "usage_usg_scaled": 0.0,
          "usage_usg_mult": 1.0,
          "usage_scoring_mult": 1.0,
          "usage_assist_mult": 1.0,
          "usage_rebound_mult": 1.0,
          "usage_threes_mult": 1.0,
          "usage_metric_mult": 1.0,
          "usage_target_rate": 0.0803745655848622,
          "usage_burden_ratio": 0.6605165307877914,
          "usage_dep_raw": 0.883476,
          "p_adj_pre_under_relief": 0.6976802319768023,
          "p_adj_pre_competitive_usage": 0.6976802319768023,
          "competitive_usage_bonus": 0.0,
          "competitive_usage_eligible": true,
          "competitive_usage_usage_gate": 0.0,
          "competitive_usage_frag_gate": 1.0,
          "competitive_usage_tight_gate": 0.44499110600299824,
          "competitive_usage_total_gate": 0.0,
          "competitive_usage_bonus_uncapped": 0.0,
          "competitive_usage_headroom": 0.011998800119987996,
          "under_relief_haircut": 0.0,
          "under_relief_haircut_min": 0.05,
          "under_relief_factor": 1.0,
          "under_relief_applied": false,
          "under_frag": 0.0,
          "under_frag_gap": 0.0,
          "under_frag_gap_usage": 0.0,
          "under_frag_dampen_amount": 0.0,
          "p_adj_pre_under_frag_dampen": 0.6976802319768023,
          "min_mean": 31.104367181436462,
          "min_std": 4.455475946392979,
          "rate_mean": 0.12168441187838291,
          "rate_std": 0.04962749165396145,
          "rate_mean_ctx": 0.12344126404988348,
          "rate_mean_ctx_raw": 0.123445755637396,
          "rate_std_ctx": 0.06889985731156409,
          "role_metrics_mult": 1.0,
          "crafted_role_workload_enabled": false,
          "role_ctx_mult": 1.0144746868709318,
          "role_ctx_mult_raw": 1.0172442226592195,
          "role_ctx_rate_mult": 1.0144377750969158,
          "role_ctx_rate_mult_raw": 1.0144746868709318,
          "role_ctx_rate_clamp_lo": 0.94,
          "role_ctx_rate_clamp_hi": 1.08,
          "role_ctx_rate_softcap_k": 1.1,
          "role_ctx_sigma_mult": 1.0094085464661056,
          "role_ctx_reason": "ok",
          "role_ctx_damp_applied": "core_ben(31m,x1.0)",
          "zero_dnp_mult": 1.0,
          "zero_dnp_debug": "no_zero_dnp_out",
          "recent_form_blend": 0.0,
          "opp_defense_strength": 1.0,
          "form_z_line": 0.8075334029123157,
          "form_series_game": 1.0,
          "form_series_mult": 1.01,
          "form_opp_defense_factor": 1.0102447882832442,
          "form_opp_defense_rel": 0.010244788283244155,
          "form_pace_factor": -0.03364828693424782,
          "form_opp_defense_adj": 1.0102447882832442,
          "form_opp_rate_shift": 0.001233989080194689,
          "games_used": 10,
          "thin_window_mult": 1.15,
          "is_playoff": false,
          "playoff_rate_applied": "off",
          "playoff_min_applied": "off",
          "role_ctx_outs_used": 1,
          "role_ctx_outs": "[\"Huerter, Kevin\"]",
          "role_ctx_bump": 0.017244222659219544,
          "role_ctx_team": "DET",
          "role_ctx_stat": "AST",
          "role_ctx_min_games": 3.0,
          "role_ctx_by_out": "[{\"out_canon\": \"kevin huerter\", \"weight\": 0.0172442226592195}]",
          "role_metrics_score": 0.0,
          "data_health_flag": "OK",
          "role_ctx_components": NaN,
          "role_ctx_component_mults": NaN,
          "role_ctx_component_reasons": NaN,
          "p_adj_pre_blowout_bypass": 0.6976802319768023,
          "blowout_bypass_applied": 1,
          "p_adj_pre_shrink": 0.6976802319768023,
          "high_prob_shrink_applied": 0,
          "p_adj_pre_subset_shift": 0.6976802319768023,
          "subset_shift_applied": "under(383)",
          "prob_floor_applied": "goblin_over(47)",
          "logit_shrink_applied": "combo(1556)",
          "p_for_cal": 0.6976802319768023,
          "p_cal_src": "p_adj",
          "p_cal": 0.7205416095753552,
          "p_for_cal_src": "p_adj",
          "p_catboost": 0.7205416095753552,
          "_zero_dnp_flip": false,
          "prop_key": "Ausar Thompson|AST|OVER|2.5|GOBLIN",
          "external_prior_score": 0.5827829453479101,
          "external_prior_n": 1,
          "external_prior_sources": "oddsapi",
          "external_prior_epsilon": 0.05,
          "is_questionable": 1,
          "q_out_frac": 0.5,
          "rotowire_game_spread": -3.5,
          "p_cal_marketed": 0.6628982808093268,
          "marketed_score": 0.0
        },
        {
          "player": "Austin Reaves",
          "tier": "GOBLIN",
          "projection_id": "11832822|Austin Reaves|RA|GOBLIN|7.5|OVER",
          "source_projection_id": 11832822,
          "game_id": 156489,
          "game_date": "2026-05-05",
          "home": 0,
          "opp": "OKC",
          "player_key": "austin reaves",
          "team": "LAL",
          "stat": "RA",
          "stat_raw": "REBS+ASTS",
          "stat_is_canonical": 1,
          "line": 7.5,
          "direction": "OVER",
          "more_allowed": 1,
          "less_allowed": 0,
          "main_line": NaN,
          "alt_line": NaN,
          "is_main": 0,
          "odds_type": "goblin",
          "start_time": "2026-05-05T20:30:00.000-04:00",
          "updated_at": "2026-05-05 21:32:13.929000+00:00",
          "spread": 15.5,
          "home_team": "OKC",
          "away_team": "LAL",
          "home_spread": -15.5,
          "away_spread": 15.5,
          "game_spread": 15.5,
          "spread_source": "rotowire",
          "spread_ok": true,
          "spread_reason": "ok",
          "minutes_s": 1.0,
          "p": 0.6254874512548745,
          "p_role": 0.6254874512548745,
          "p_adj": 0.6569003978776599,
          "p_close": 0.71007899210079,
          "p_close_raw": 0.71007899210079,
          "p_close_role": 0.71007899210079,
          "q_blowout": 0.6882702956802265,
          "q_blowout_spread_only": 0.5946802993599825,
          "q_blowout_team_adj": 0.0033866897965620616,
          "q_blowout_matchup_adj": 0.09020330652368187,
          "blowout_minute_drop_base": 5.864784766762325,
          "blowout_minute_drop": 4.574532118074614,
          "blowout_rule_minute_drop_mult": 0.78,
          "blowout_rule_sensitivity_mult": 0.92,
          "blowout_rule_count": 1,
          "blowout_rules_applied": "combo_scoring_over_high_q_structural_v1",
          "minutes_s_blowout": 0.5888,
          "under_blowout_sens_mult": 0.5888,
          "under_blowout_sens_eligible": false,
          "minutes_s_close": 0.35,
          "is_star": true,
          "rotation_tier": "star",
          "blowout_minute_delta": -5.864784766762325,
          "blowout_base_min_for_curve": 35.2313741670083,
          "fragility": 0.11440030979370562,
          "fragility_abs": 0.08123325667433262,
          "fragility_gap_core": 0.08459154084591547,
          "fragility_gap_usage": 0.08123325667433262,
          "fragility_gap_dir": 0.08123325667433262,
          "usage_dep": 0.9602999999999999,
          "usage_dep_capped": 0.9602999999999999,
          "usage_dep_cap": 1.06,
          "usage_dep_eff": 0.9602999999999999,
          "usage_risk_gate": 1.0,
          "usage_baseline": 1.0,
          "usage_producer_mult": 0.99,
          "usage_pressure_mult": 0.97,
          "usage_usg_pct": NaN,
          "usage_usg_scaled": 0.0,
          "usage_usg_mult": 1.0,
          "usage_scoring_mult": 1.0,
          "usage_assist_mult": 1.0,
          "usage_rebound_mult": 1.0,
          "usage_threes_mult": 1.0,
          "usage_metric_mult": 1.0,
          "usage_target_rate": 0.21287844080243745,
          "usage_burden_ratio": 0.8007915841995134,
          "usage_dep_raw": 0.9602999999999999,
          "p_adj_pre_under_relief": 0.6254874512548745,
          "p_adj_pre_competitive_usage": 0.6254874512548745,
          "competitive_usage_bonus": 0.0,
          "competitive_usage_eligible": false,
          "competitive_usage_usage_gate": 0.0,
          "competitive_usage_frag_gate": 0.06999612757867969,
          "competitive_usage_tight_gate": 0.0,
          "competitive_usage_total_gate": 0.0,
          "competitive_usage_bonus_uncapped": 0.0,
          "competitive_usage_headroom": 0.08459154084591547,
          "under_relief_haircut": 0.0,
          "under_relief_haircut_min": 0.05,
          "under_relief_factor": 1.0,
          "under_relief_applied": false,
          "under_frag": 0.0,
          "under_frag_gap": 0.0,
          "under_frag_gap_usage": 0.0,
          "under_frag_dampen_amount": 0.0,
          "p_adj_pre_under_frag_dampen": 0.6254874512548745,
          "min_mean": 35.2313741670083,
          "min_std": 4.159130466057146,
          "rate_mean": 0.2658350125085728,
          "rate_std": 0.07035630572422984,
          "rate_mean_ctx": 0.2658350125085728,
          "rate_mean_ctx_raw": 0.2658350125085728,
          "rate_std_ctx": 0.07597425673630959,
          "role_metrics_mult": 1.0,
          "crafted_role_workload_enabled": false,
          "role_ctx_mult": 1.0,
          "role_ctx_mult_raw": 1.0,
          "role_ctx_rate_mult": 1.0,
          "role_ctx_rate_mult_raw": 1.0,
          "role_ctx_rate_clamp_lo": 0.94,
          "role_ctx_rate_clamp_hi": 1.08,
          "role_ctx_rate_softcap_k": 1.1,
          "role_ctx_sigma_mult": 1.0,
          "role_ctx_reason": "no_outs",
          "role_ctx_damp_applied": "star_ben(35m,x0.4)",
          "zero_dnp_mult": 1.0,
          "zero_dnp_debug": "no_outs_or_gl",
          "recent_form_blend": 0.0,
          "opp_defense_strength": 1.0,
          "form_z_line": 0.7660688668660678,
          "form_series_game": 1.0,
          "form_series_mult": 1.01,
          "form_opp_defense_factor": 0.9964719355034891,
          "form_opp_defense_rel": -0.0035280644965108854,
          "form_pace_factor": -0.0499002576594928,
          "form_opp_defense_adj": 0.9964719355034891,
          "form_opp_rate_shift": -0.0009412036969080884,
          "games_used": 10,
          "thin_window_mult": 1.15,
          "is_playoff": false,
          "playoff_rate_applied": "off",
          "playoff_min_applied": "off",
          "role_ctx_outs_used": 0,
          "role_ctx_outs": "[]",
          "role_ctx_bump": 0.0,
          "role_ctx_team": NaN,
          "role_ctx_stat": NaN,
          "role_ctx_min_games": NaN,
          "role_ctx_by_out": "[]",
          "role_metrics_score": 0.0,
          "data_health_flag": "OK",
          "role_ctx_components": "[\"REB\", \"AST\"]",
          "role_ctx_component_mults": "[1.0, 1.0]",
          "role_ctx_component_reasons": "[\"no_outs\", \"no_outs\"]",
          "p_adj_pre_blowout_bypass": 0.6254874512548745,
          "blowout_bypass_applied": 1,
          "p_adj_pre_shrink": 0.6254874512548745,
          "high_prob_shrink_applied": 0,
          "p_adj_pre_subset_shift": 0.6254874512548745,
          "subset_shift_applied": "under(383)",
          "prob_floor_applied": "goblin_over(47)",
          "logit_shrink_applied": "combo(1556)",
          "p_for_cal": 0.6133973147905263,
          "p_cal_src": "p_adj",
          "p_cal": 0.7528041323651813,
          "p_for_cal_src": "p_adj",
          "p_catboost": 0.7528041323651813,
          "_zero_dnp_flip": false,
          "prop_key": "Austin Reaves|RA|OVER|7.5|GOBLIN",
          "external_prior_score": 0.8700616617426719,
          "external_prior_n": 1,
          "external_prior_sources": "oddsapi",
          "external_prior_epsilon": 0.05,
          "is_questionable": 0,
          "q_out_frac": 0.0,
          "rotowire_game_spread": 15.5,
          "p_cal_marketed": 0.7076358844232704,
          "marketed_score": 0.0
        },
        {
          "player": "Kelly Oubre",
          "tier": "STANDARD",
          "projection_id": "11879128|Kelly Oubre|PTS|STANDARD|11|OVER",
          "source_projection_id": 11879128,
          "game_id": 156676,
          "game_date": "2026-05-06",
          "home": 0,
          "opp": "NYK",
          "player_key": "kelly oubre",
          "team": "PHI",
          "stat": "PTS",
          "stat_raw": "POINTS",
          "stat_is_canonical": 1,
          "line": 11.0,
          "direction": "OVER",
          "more_allowed": 1,
          "less_allowed": 0,
          "main_line": NaN,
          "alt_line": NaN,
          "is_main": 0,
          "odds_type": "standard",
          "start_time": "2026-05-06T19:00:00.000-04:00",
          "updated_at": "2026-05-05 18:09:50.952000+00:00",
          "spread": 0.0,
          "home_team": NaN,
          "away_team": NaN,
          "home_spread": NaN,
          "away_spread": NaN,
          "game_spread": NaN,
          "spread_source": "rotowire",
          "spread_ok": false,
          "spread_reason": "no_game_for_team_date",
          "minutes_s": 1.0,
          "p": 0.5598940105989401,
          "p_role": 0.5598940105989401,
          "p_adj": 0.5598940105989401,
          "p_close": 0.5791920807919209,
          "p_close_raw": 0.5791920807919209,
          "p_close_role": 0.5791920807919209,
          "q_blowout": 0.24063194727365875,
          "q_blowout_spread_only": 0.23727785186827832,
          "q_blowout_team_adj": 0.0033540954053804238,
          "q_blowout_matchup_adj": 0.0,
          "blowout_minute_drop_base": 5.6046040274699465,
          "blowout_minute_drop": 5.6046040274699465,
          "blowout_rule_minute_drop_mult": 1.0,
          "blowout_rule_sensitivity_mult": 1.0,
          "blowout_rule_count": 0,
          "blowout_rules_applied": "",
          "minutes_s_blowout": 0.76,
          "under_blowout_sens_mult": 0.76,
          "under_blowout_sens_eligible": false,
          "minutes_s_close": 0.35,
          "is_star": true,
          "rotation_tier": "star",
          "blowout_minute_delta": -5.6046040274699465,
          "blowout_base_min_for_curve": 34.30215724096409,
          "fragility": 0.032579435051833944,
          "fragility_abs": 0.018869750778696945,
          "fragility_gap_core": 0.0192980701929808,
          "fragility_gap_usage": 0.018869750778696945,
          "fragility_gap_dir": 0.018869750778696945,
          "usage_dep": 0.9602999999999999,
          "usage_dep_capped": 0.9602999999999999,
          "usage_dep_cap": 1.06,
          "usage_dep_eff": 0.9778050649624208,
          "usage_risk_gate": 0.5590663737425485,
          "usage_baseline": 1.0,
          "usage_producer_mult": 0.99,
          "usage_pressure_mult": 0.97,
          "usage_usg_pct": NaN,
          "usage_usg_scaled": 0.0,
          "usage_usg_mult": 1.0,
          "usage_scoring_mult": 1.0,
          "usage_assist_mult": 1.0,
          "usage_rebound_mult": 1.0,
          "usage_threes_mult": 1.0,
          "usage_metric_mult": 1.0,
          "usage_target_rate": 0.32067953985306946,
          "usage_burden_ratio": 0.8368744692558788,
          "usage_dep_raw": 0.9602999999999999,
          "p_adj_pre_under_relief": 0.5598940105989401,
          "p_adj_pre_competitive_usage": 0.5598940105989401,
          "competitive_usage_bonus": 0.0,
          "competitive_usage_eligible": true,
          "competitive_usage_usage_gate": 0.0,
          "competitive_usage_frag_gate": 1.0,
          "competitive_usage_tight_gate": 0.0,
          "competitive_usage_total_gate": 0.0,
          "competitive_usage_bonus_uncapped": 0.0,
          "competitive_usage_headroom": 0.0192980701929808,
          "under_relief_haircut": 0.0,
          "under_relief_haircut_min": 0.05,
          "under_relief_factor": 1.0,
          "under_relief_applied": false,
          "under_frag": 0.0,
          "under_frag_gap": 0.0,
          "under_frag_gap_usage": 0.0,
          "under_frag_dampen_amount": 0.0,
          "p_adj_pre_under_frag_dampen": 0.5598940105989401,
          "min_mean": 34.30215724096409,
          "min_std": 4.499612973559923,
          "rate_mean": 0.38318714650024766,
          "rate_std": 0.169473528485527,
          "rate_mean_ctx": 0.38318714650024766,
          "rate_mean_ctx_raw": 0.38318714650024766,
          "rate_std_ctx": 0.25336292508586283,
          "role_metrics_mult": 1.0,
          "crafted_role_workload_enabled": false,
          "role_ctx_mult": 1.0,
          "role_ctx_mult_raw": 1.0,
          "role_ctx_rate_mult": 1.0,
          "role_ctx_rate_mult_raw": 1.0,
          "role_ctx_rate_clamp_lo": 0.94,
          "role_ctx_rate_clamp_hi": 1.08,
          "role_ctx_rate_softcap_k": 1.1,
          "role_ctx_sigma_mult": 1.0,
          "role_ctx_reason": "no_outs",
          "role_ctx_damp_applied": "star_ben(34m,x0.4)",
          "zero_dnp_mult": 1.0,
          "zero_dnp_debug": "no_outs_or_gl",
          "recent_form_blend": 0.0,
          "opp_defense_strength": 1.0,
          "form_z_line": 0.3688340427308465,
          "form_series_game": 1.0,
          "form_series_mult": 1.01,
          "form_opp_defense_factor": 1.0,
          "form_opp_defense_rel": 0.0,
          "form_pace_factor": 0.0,
          "form_opp_defense_adj": 1.0,
          "form_opp_rate_shift": 0.0,
          "games_used": 10,
          "thin_window_mult": 1.15,
          "is_playoff": false,
          "playoff_rate_applied": "off",
          "playoff_min_applied": "off",
          "role_ctx_outs_used": 0,
          "role_ctx_outs": "[]",
          "role_ctx_bump": 0.0,
          "role_ctx_team": NaN,
          "role_ctx_stat": NaN,
          "role_ctx_min_games": NaN,
          "role_ctx_by_out": "[]",
          "role_metrics_score": 0.0,
          "data_health_flag": "OK",
          "role_ctx_components": "[\"PTS\"]",
          "role_ctx_component_mults": "[1.0]",
          "role_ctx_component_reasons": "[\"no_outs\"]",
          "p_adj_pre_blowout_bypass": 0.5598940105989401,
          "blowout_bypass_applied": 0,
          "p_adj_pre_shrink": 0.5598940105989401,
          "high_prob_shrink_applied": 0,
          "p_adj_pre_subset_shift": 0.5598940105989401,
          "subset_shift_applied": "under(383)",
          "prob_floor_applied": "goblin_over(47)",
          "logit_shrink_applied": "combo(1556)",
          "p_for_cal": 0.5598940105989401,
          "p_cal_src": "p_adj",
          "p_cal": 0.7502503805493624,
          "p_for_cal_src": "p_adj",
          "p_catboost": 0.7502503805493624,
          "_zero_dnp_flip": false,
          "prop_key": "Kelly Oubre|PTS|OVER|11.0|STANDARD",
          "external_prior_score": 0.0,
          "external_prior_n": 0,
          "external_prior_sources": "",
          "external_prior_epsilon": 0.05,
          "is_questionable": 0,
          "q_out_frac": 0.0,
          "rotowire_game_spread": NaN,
          "p_cal_marketed": 0.7052353577164007,
          "marketed_score": 0.7052353577164007
        },
        {
          "player": "Isaiah Joe",
          "tier": "STANDARD",
          "projection_id": "11870481|Isaiah Joe|PTS|STANDARD|7|OVER",
          "source_projection_id": 11870481,
          "game_id": 156489,
          "game_date": "2026-05-05",
          "home": 1,
          "opp": "LAL",
          "player_key": "isaiah joe",
          "team": "OKC",
          "stat": "PTS",
          "stat_raw": "POINTS",
          "stat_is_canonical": 1,
          "line": 7.0,
          "direction": "OVER",
          "more_allowed": 1,
          "less_allowed": 0,
          "main_line": NaN,
          "alt_line": NaN,
          "is_main": 0,
          "odds_type": "standard",
          "start_time": "2026-05-05T20:30:00.000-04:00",
          "updated_at": "2026-05-05 18:28:14.649000+00:00",
          "spread": -15.5,
          "home_team": "OKC",
          "away_team": "LAL",
          "home_spread": -15.5,
          "away_spread": 15.5,
          "game_spread": -15.5,
          "spread_source": "rotowire",
          "spread_ok": true,
          "spread_reason": "ok",
          "minutes_s": 1.0,
          "p": 0.8281671832816718,
          "p_role": 0.8302669733026697,
          "p_adj": 0.7545645025240723,
          "p_close": 0.8261673832616738,
          "p_close_raw": 0.8237676232376763,
          "p_close_role": 0.8261673832616738,
          "q_blowout": 0.6882702956802266,
          "q_blowout_spread_only": 0.5946802993599826,
          "q_blowout_team_adj": 0.0033866897965620616,
          "q_blowout_matchup_adj": 0.09020330652368187,
          "blowout_minute_drop_base": -0.042355996742529545,
          "blowout_minute_drop": 0.0,
          "blowout_rule_minute_drop_mult": 0.78,
          "blowout_rule_sensitivity_mult": 0.92,
          "blowout_rule_count": 1,
          "blowout_rules_applied": "combo_scoring_over_high_q_structural_v1",
          "minutes_s_blowout": 0.5888,
          "under_blowout_sens_mult": 0.5888,
          "under_blowout_sens_eligible": false,
          "minutes_s_close": 0.35,
          "is_star": false,
          "rotation_tier": "bench",
          "blowout_minute_delta": 0.042355996742529545,
          "blowout_base_min_for_curve": 14.134442868776679,
          "fragility": 0.0,
          "fragility_abs": 0.0,
          "fragility_gap_core": 0.0,
          "fragility_gap_usage": 0.0,
          "fragility_gap_dir": 0.0,
          "usage_dep": 0.97,
          "usage_dep_capped": 0.97,
          "usage_dep_cap": 1.06,
          "usage_dep_eff": 0.97,
          "usage_risk_gate": 1.0,
          "usage_baseline": 1.0,
          "usage_producer_mult": 1.0,
          "usage_pressure_mult": 0.97,
          "usage_usg_pct": NaN,
          "usage_usg_scaled": 0.0,
          "usage_usg_mult": 1.0,
          "usage_scoring_mult": 1.0,
          "usage_assist_mult": 1.0,
          "usage_rebound_mult": 1.0,
          "usage_threes_mult": 1.0,
          "usage_metric_mult": 1.0,
          "usage_target_rate": 0.2940859617747836,
          "usage_burden_ratio": 0.41927053864109337,
          "usage_dep_raw": 0.97,
          "p_adj_pre_under_relief": 0.8302669733026697,
          "p_adj_pre_competitive_usage": 0.8302669733026697,
          "competitive_usage_bonus": 0.0,
          "competitive_usage_eligible": false,
          "competitive_usage_usage_gate": 0.0,
          "competitive_usage_frag_gate": 1.0,
          "competitive_usage_tight_gate": 0.0,
          "competitive_usage_total_gate": 0.0,
          "competitive_usage_bonus_uncapped": 0.0,
          "competitive_usage_headroom": 0.0,
          "under_relief_haircut": 0.0,
          "under_relief_haircut_min": 0.05,
          "under_relief_factor": 1.0,
          "under_relief_applied": false,
          "under_frag": 0.0,
          "under_frag_gap": 0.0,
          "under_frag_gap_usage": 0.0,
          "under_frag_dampen_amount": 0.0,
          "p_adj_pre_under_frag_dampen": 0.8302669733026697,
          "min_mean": 14.134442868776679,
          "min_std": 4.849220166203973,
          "rate_mean": 0.7014229111541007,
          "rate_std": 0.25757517535183716,
          "rate_mean_ctx": 0.7070738922130927,
          "rate_mean_ctx_raw": 0.7068376358347864,
          "rate_std_ctx": 0.3870071000862138,
          "role_metrics_mult": 1.0,
          "crafted_role_workload_enabled": false,
          "role_ctx_mult": 1.0077196290491517,
          "role_ctx_mult_raw": 1.0088932052683164,
          "role_ctx_rate_mult": 1.0080564534878025,
          "role_ctx_rate_mult_raw": 1.0077196290491517,
          "role_ctx_rate_clamp_lo": 0.94,
          "role_ctx_rate_clamp_hi": 1.08,
          "role_ctx_rate_softcap_k": 1.1,
          "role_ctx_sigma_mult": 1.0050177588819487,
          "role_ctx_reason": "ok",
          "role_ctx_damp_applied": "",
          "zero_dnp_mult": 1.6840114937965787,
          "zero_dnp_debug": "zero_dnp:Williams, Jalen(dnp=1,out_min=26,pl_min=14,x1.684,missed=0)",
          "recent_form_blend": 0.0,
          "opp_defense_strength": 1.0,
          "form_z_line": 0.7950530809857588,
          "form_series_game": 1.0,
          "form_series_mult": 1.01,
          "form_opp_defense_factor": 1.0019896782422537,
          "form_opp_defense_rel": 0.001989678242253712,
          "form_pace_factor": -0.0499002576594928,
          "form_opp_defense_adj": 1.0019896782422537,
          "form_opp_rate_shift": 0.0013928346122186186,
          "games_used": 10,
          "thin_window_mult": 1.15,
          "is_playoff": false,
          "playoff_rate_applied": "off",
          "playoff_min_applied": "off",
          "role_ctx_outs_used": 1,
          "role_ctx_outs": "[\"Sorber, Thomas\", \"Williams, Jalen\"]",
          "role_ctx_bump": 0.008893205268316384,
          "role_ctx_team": "OKC",
          "role_ctx_stat": "PTS",
          "role_ctx_min_games": 3.0,
          "role_ctx_by_out": "[{\"out_canon\": \"jalen williams\", \"weight\": 0.0088932052683164}]",
          "role_metrics_score": 0.0,
          "data_health_flag": "OK",
          "role_ctx_components": "[\"PTS\", \"AST\"]",
          "role_ctx_component_mults": "[1.0088932052683164, 1.0118974177139788]",
          "role_ctx_component_reasons": "[\"ok\", \"ok\"]",
          "p_adj_pre_blowout_bypass": 0.8302669733026697,
          "blowout_bypass_applied": 1,
          "p_adj_pre_shrink": 0.8302669733026697,
          "high_prob_shrink_applied": 1,
          "p_adj_pre_subset_shift": 0.7545645025240723,
          "subset_shift_applied": "under(383)",
          "prob_floor_applied": "goblin_over(47)",
          "logit_shrink_applied": "combo(1556)",
          "p_for_cal": 0.7545645025240723,
          "p_cal_src": "p_adj",
          "p_cal": 0.7435491937954248,
          "p_for_cal_src": "p_adj",
          "p_catboost": 0.7178468067619144,
          "_zero_dnp_flip": false,
          "prop_key": "Isaiah Joe|PTS|OVER|7.0|STANDARD",
          "external_prior_score": 0.0,
          "external_prior_n": 0,
          "external_prior_sources": "oddsapi",
          "external_prior_epsilon": 0.05,
          "is_questionable": 0,
          "q_out_frac": 0.0,
          "rotowire_game_spread": -15.5,
          "p_cal_marketed": 0.6989362421676993,
          "marketed_score": 0.6989362421676993
        },
        {
          "player": "Cade Cunningham",
          "tier": "DEMON",
          "projection_id": "11892802|Cade Cunningham|REB|DEMON|5.5|OVER",
          "source_projection_id": 11892802,
          "game_id": 156892,
          "game_date": "2026-05-05",
          "home": 1,
          "opp": "CLE",
          "player_key": "cade cunningham",
          "team": "DET",
          "stat": "REB",
          "stat_raw": "REBOUNDS",
          "stat_is_canonical": 1,
          "line": 5.5,
          "direction": "OVER",
          "more_allowed": 1,
          "less_allowed": 0,
          "main_line": NaN,
          "alt_line": NaN,
          "is_main": 0,
          "odds_type": "demon",
          "start_time": "2026-05-05T19:00:00.000-04:00",
          "updated_at": "2026-05-05 19:03:03.575000+00:00",
          "spread": -3.5,
          "home_team": "DET",
          "away_team": "CLE",
          "home_spread": -3.5,
          "away_spread": 3.5,
          "game_spread": -3.5,
          "spread_source": "rotowire",
          "spread_ok": true,
          "spread_reason": "ok",
          "minutes_s": 0.7,
          "p": 0.4982001799820018,
          "p_role": 0.4982001799820018,
          "p_adj": 0.49820017998200183,
          "p_close": 0.5052994700529947,
          "p_close_raw": 0.5052994700529947,
          "p_close_role": 0.5052994700529947,
          "q_blowout": 0.13550088939970018,
          "q_blowout_spread_only": 0.26070104207215794,
          "q_blowout_team_adj": -0.007070125862806323,
          "q_blowout_matchup_adj": -0.11813002680965147,
          "blowout_minute_drop_base": 7.382744453900399,
          "blowout_minute_drop": 7.382744453900399,
          "blowout_rule_minute_drop_mult": 1.0,
          "blowout_rule_sensitivity_mult": 1.0,
          "blowout_rule_count": 0,
          "blowout_rules_applied": "",
          "minutes_s_blowout": 0.5319999999999999,
          "under_blowout_sens_mult": 0.76,
          "under_blowout_sens_eligible": false,
          "minutes_s_close": 0.24499999999999997,
          "is_star": true,
          "rotation_tier": "star",
          "blowout_minute_delta": -7.382744453900399,
          "blowout_base_min_for_curve": 40.65265876392999,
          "fragility": 0.014049668546551921,
          "fragility_abs": 0.007099290070992914,
          "fragility_gap_core": 0.007099290070992914,
          "fragility_gap_usage": 0.007099290070992914,
          "fragility_gap_dir": 0.007099290070992914,
          "usage_dep": 0.7722,
          "usage_dep_capped": 0.7722,
          "usage_dep_cap": 1.02,
          "usage_dep_eff": 1.0,
          "usage_risk_gate": 0.0,
          "usage_baseline": 0.78,
          "usage_producer_mult": 0.99,
          "usage_pressure_mult": 1.0,
          "usage_usg_pct": NaN,
          "usage_usg_scaled": 0.0,
          "usage_usg_mult": 1.0,
          "usage_scoring_mult": 1.0,
          "usage_assist_mult": 1.0,
          "usage_rebound_mult": 1.0,
          "usage_threes_mult": 1.0,
          "usage_metric_mult": 1.0,
          "usage_target_rate": 0.13529250403862889,
          "usage_burden_ratio": 0.9718593205131953,
          "usage_dep_raw": 0.7722,
          "p_adj_pre_under_relief": 0.4982001799820018,
          "p_adj_pre_competitive_usage": 0.4982001799820018,
          "competitive_usage_bonus": 0.0,
          "competitive_usage_eligible": false,
          "competitive_usage_usage_gate": 0.0,
          "competitive_usage_frag_gate": 1.0,
          "competitive_usage_tight_gate": 0.44499110600299824,
          "competitive_usage_total_gate": 0.0,
          "competitive_usage_bonus_uncapped": 0.0,
          "competitive_usage_headroom": 0.007099290070992914,
          "under_relief_haircut": 0.0,
          "under_relief_haircut_min": 0.05,
          "under_relief_factor": 1.0,
          "under_relief_applied": false,
          "under_frag": 0.0,
          "under_frag_gap": 0.0,
          "under_frag_gap_usage": 0.0,
          "under_frag_dampen_amount": 0.0,
          "p_adj_pre_under_frag_dampen": 0.4982001799820018,
          "min_mean": 40.65265876392999,
          "min_std": 1.8238108685234478,
          "rate_mean": 0.13920996710427902,
          "rate_std": 0.08525844149624863,
          "rate_mean_ctx": 0.13920996710427902,
          "rate_mean_ctx_raw": 0.13920996710427902,
          "rate_std_ctx": 0.09814525492840659,
          "role_metrics_mult": 1.0,
          "crafted_role_workload_enabled": false,
          "role_ctx_mult": 1.0,
          "role_ctx_mult_raw": 1.0,
          "role_ctx_rate_mult": 1.0,
          "role_ctx_rate_mult_raw": 1.0,
          "role_ctx_rate_clamp_lo": 0.94,
          "role_ctx_rate_clamp_hi": 1.08,
          "role_ctx_rate_softcap_k": 1.1,
          "role_ctx_sigma_mult": 1.0,
          "role_ctx_reason": "ok",
          "role_ctx_damp_applied": "star_ben(41m,x0.4),demon(x0.0)",
          "zero_dnp_mult": 1.0,
          "zero_dnp_debug": "no_zero_dnp_out",
          "recent_form_blend": 0.0,
          "opp_defense_strength": 1.0,
          "form_z_line": 0.0547240158266194,
          "form_series_game": 1.0,
          "form_series_mult": 1.01,
          "form_opp_defense_factor": 0.9946539659807287,
          "form_opp_defense_rel": -0.005346034019271251,
          "form_pace_factor": -0.03364828693424782,
          "form_opp_defense_adj": 0.9946539659807287,
          "form_opp_rate_shift": -0.0007482212361434593,
          "games_used": 10,
          "thin_window_mult": 1.15,
          "is_playoff": false,
          "playoff_rate_applied": "off",
          "playoff_min_applied": "off",
          "role_ctx_outs_used": 1,
          "role_ctx_outs": "[\"Huerter, Kevin\"]",
          "role_ctx_bump": 0.019245536667791607,
          "role_ctx_team": "DET",
          "role_ctx_stat": "REB",
          "role_ctx_min_games": 3.0,
          "role_ctx_by_out": "[{\"out_canon\": \"kevin huerter\", \"weight\": 0.0192455366677916}]",
          "role_metrics_score": 0.0,
          "data_health_flag": "OK",
          "role_ctx_components": NaN,
          "role_ctx_component_mults": NaN,
          "role_ctx_component_reasons": NaN,
          "p_adj_pre_blowout_bypass": 0.4982001799820018,
          "blowout_bypass_applied": 1,
          "p_adj_pre_shrink": 0.4982001799820018,
          "high_prob_shrink_applied": 0,
          "p_adj_pre_subset_shift": 0.4982001799820018,
          "subset_shift_applied": "under(383)",
          "prob_floor_applied": "goblin_over(47)",
          "logit_shrink_applied": "combo(1556)",
          "p_for_cal": 0.49820017998200183,
          "p_cal_src": "p_adj",
          "p_cal": 0.658081963305733,
          "p_for_cal_src": "p_adj",
          "p_catboost": 0.658081963305733,
          "_zero_dnp_flip": false,
          "prop_key": "Cade Cunningham|REB|OVER|5.5|DEMON",
          "external_prior_score": 0.0,
          "external_prior_n": 0,
          "external_prior_sources": "oddsapi",
          "external_prior_epsilon": 0.05,
          "is_questionable": 1,
          "q_out_frac": 0.5,
          "rotowire_game_spread": -3.5,
          "p_cal_marketed": 0.5133039313784717,
          "marketed_score": 0.0
        }
      ],
      "hit_prob": 0.17262043657377227,
      "hit_prob_raw": 0.11282381475409953,
      "payout_mult": 2.1445422618829917,
      "ev": 0.3701918214971471,
      "n_legs": 5,
      "high_confidence": true
    },
    {
      "label": "4-leg",
      "legs": [
        {
          "player": "Chet Holmgren",
          "tier": "GOBLIN",
          "projection_id": "11833354|Chet Holmgren|PA|GOBLIN|14.5|OVER",
          "source_projection_id": 11833354,
          "game_id": 156489,
          "game_date": "2026-05-05",
          "home": 1,
          "opp": "LAL",
          "player_key": "chet holmgren",
          "team": "OKC",
          "stat": "PA",
          "stat_raw": "PTS+ASTS",
          "stat_is_canonical": 1,
          "line": 14.5,
          "direction": "OVER",
          "more_allowed": 1,
          "less_allowed": 0,
          "main_line": NaN,
          "alt_line": NaN,
          "is_main": 0,
          "odds_type": "goblin",
          "start_time": "2026-05-05T20:30:00.000-04:00",
          "updated_at": "2026-05-05 12:08:03.256000+00:00",
          "spread": -15.5,
          "home_team": "OKC",
          "away_team": "LAL",
          "home_spread": -15.5,
          "away_spread": 15.5,
          "game_spread": -15.5,
          "spread_source": "rotowire",
          "spread_ok": true,
          "spread_reason": "ok",
          "minutes_s": 1.0,
          "p": 0.7807719228077192,
          "p_role": 0.7978702129787021,
          "p_adj": 0.7794810536472467,
          "p_close": 0.8438656134386562,
          "p_close_raw": 0.8297670232976703,
          "p_close_role": 0.8438656134386562,
          "q_blowout": 0.6882702956802266,
          "q_blowout_spread_only": 0.5946802993599826,
          "q_blowout_team_adj": 0.0033866897965620616,
          "q_blowout_matchup_adj": 0.09020330652368187,
          "blowout_minute_drop_base": 4.4972370649989735,
          "blowout_minute_drop": 3.5078449106991996,
          "blowout_rule_minute_drop_mult": 0.78,
          "blowout_rule_sensitivity_mult": 0.92,
          "blowout_rule_count": 1,
          "blowout_rules_applied": "combo_scoring_over_high_q_structural_v1",
          "minutes_s_blowout": 0.5888,
          "under_blowout_sens_mult": 0.5888,
          "under_blowout_sens_eligible": false,
          "minutes_s_close": 0.35,
          "is_star": false,
          "rotation_tier": "starter",
          "blowout_minute_delta": -4.4972370649989735,
          "blowout_base_min_for_curve": 30.347275232139186,
          "fragility": 0.052870430712720046,
          "fragility_abs": 0.04461553844615547,
          "fragility_gap_core": 0.045995400459954094,
          "fragility_gap_usage": 0.04461553844615547,
          "fragility_gap_dir": 0.04461553844615547,
          "usage_dep": 0.97,
          "usage_dep_capped": 0.97,
          "usage_dep_cap": 1.06,
          "usage_dep_eff": 0.97,
          "usage_risk_gate": 1.0,
          "usage_baseline": 1.0,
          "usage_producer_mult": 1.0,
          "usage_pressure_mult": 0.97,
          "usage_usg_pct": NaN,
          "usage_usg_scaled": 0.0,
          "usage_usg_mult": 1.0,
          "usage_scoring_mult": 1.0,
          "usage_assist_mult": 1.0,
          "usage_rebound_mult": 1.0,
          "usage_threes_mult": 1.0,
          "usage_metric_mult": 1.0,
          "usage_target_rate": 0.47780236904576595,
          "usage_burden_ratio": 0.6673775321407459,
          "usage_dep_raw": 0.97,
          "p_adj_pre_under_relief": 0.7978702129787021,
          "p_adj_pre_competitive_usage": 0.7978702129787021,
          "competitive_usage_bonus": 0.0,
          "competitive_usage_eligible": true,
          "competitive_usage_usage_gate": 0.0,
          "competitive_usage_frag_gate": 0.8391196160909995,
          "competitive_usage_tight_gate": 0.0,
          "competitive_usage_total_gate": 0.0,
          "competitive_usage_bonus_uncapped": 0.0,
          "competitive_usage_headroom": 0.045995400459954094,
          "under_relief_haircut": 0.0,
          "under_relief_haircut_min": 0.05,
          "under_relief_factor": 1.0,
          "under_relief_applied": false,
          "under_frag": 0.0,
          "under_frag_gap": 0.0,
          "under_frag_gap_usage": 0.0,
          "under_frag_dampen_amount": 0.0,
          "p_adj_pre_under_frag_dampen": 0.7978702129787021,
          "min_mean": 30.347275232139186,
          "min_std": 3.3750137335589,
          "rate_mean": 0.7159401478697073,
          "rate_std": 0.1664887835570554,
          "rate_mean_ctx": 0.7349193051505392,
          "rate_mean_ctx_raw": 0.7368987646173385,
          "rate_std_ctx": 0.21559134901915827,
          "role_metrics_mult": 1.0,
          "crafted_role_workload_enabled": false,
          "role_ctx_mult": 1.0292742582043959,
          "role_ctx_mult_raw": 1.0378183495582545,
          "role_ctx_rate_mult": 1.0265094188910968,
          "role_ctx_rate_mult_raw": 1.0292742582043959,
          "role_ctx_rate_clamp_lo": 0.94,
          "role_ctx_rate_clamp_hi": 1.08,
          "role_ctx_rate_softcap_k": 1.1,
          "role_ctx_sigma_mult": 1.0190282678328573,
          "role_ctx_reason": "ok_combo",
          "role_ctx_damp_applied": "core_ben(30m,x1.0)",
          "zero_dnp_mult": 1.0,
          "zero_dnp_debug": "no_zero_dnp_out",
          "recent_form_blend": 0.0,
          "opp_defense_strength": 1.0,
          "form_z_line": 1.4154501490160718,
          "form_series_game": 1.0,
          "form_series_mult": 1.01,
          "form_opp_defense_factor": 1.003477712844646,
          "form_opp_defense_rel": 0.0034777128446459304,
          "form_pace_factor": -0.0499002576594928,
          "form_opp_defense_adj": 1.003477712844646,
          "form_opp_rate_shift": 0.0024812053286027425,
          "games_used": 10,
          "thin_window_mult": 1.15,
          "is_playoff": false,
          "playoff_rate_applied": "off",
          "playoff_min_applied": "off",
          "role_ctx_outs_used": 2,
          "role_ctx_outs": "[\"Sorber, Thomas\", \"Williams, Jalen\"]",
          "role_ctx_bump": 0.03817677207964798,
          "role_ctx_team": "OKC",
          "role_ctx_stat": "REB",
          "role_ctx_min_games": 3.0,
          "role_ctx_by_out": "[{\"out_canon\": \"jalen williams\", \"weight\": 0.0166503622065423}, {\"out_canon\": \"jalen williams\", \"weight\": 0.0215264098731057}]",
          "role_metrics_score": 0.0,
          "data_health_flag": "OK",
          "role_ctx_components": "[\"PTS\", \"AST\"]",
          "role_ctx_component_mults": "[1.0166503622065424, 1.0215264098731058]",
          "role_ctx_component_reasons": "[\"ok\", \"ok\"]",
          "p_adj_pre_blowout_bypass": 0.7978702129787021,
          "blowout_bypass_applied": 1,
          "p_adj_pre_shrink": 0.7978702129787021,
          "high_prob_shrink_applied": 1,
          "p_adj_pre_subset_shift": 0.7525689966906779,
          "subset_shift_applied": "under(383)",
          "prob_floor_applied": "goblin_over(47)",
          "logit_shrink_applied": "combo(1556)",
          "p_for_cal": 0.7312796746434559,
          "p_cal_src": "p_adj",
          "p_cal": 0.7430529924711826,
          "p_for_cal_src": "p_adj",
          "p_catboost": 0.7430529924711826,
          "_zero_dnp_flip": false,
          "prop_key": "Chet Holmgren|PA|OVER|14.5|GOBLIN",
          "external_prior_score": 0.9640275800758169,
          "external_prior_n": 1,
          "external_prior_sources": "oddsapi",
          "external_prior_epsilon": 0.05,
          "is_questionable": 0,
          "q_out_frac": 0.0,
          "rotowire_game_spread": -15.5,
          "p_cal_marketed": 0.728191932621759,
          "marketed_score": 0.0
        },
        {
          "player": "Daniss Jenkins",
          "tier": "GOBLIN",
          "projection_id": "11867411|Daniss Jenkins|REB|GOBLIN|1.5|OVER",
          "source_projection_id": 11867411,
          "game_id": 156892,
          "game_date": "2026-05-05",
          "home": 1,
          "opp": "CLE",
          "player_key": "daniss jenkins",
          "team": "DET",
          "stat": "REB",
          "stat_raw": "REBOUNDS",
          "stat_is_canonical": 1,
          "line": 1.5,
          "direction": "OVER",
          "more_allowed": 1,
          "less_allowed": 0,
          "main_line": NaN,
          "alt_line": NaN,
          "is_main": 0,
          "odds_type": "goblin",
          "start_time": "2026-05-05T19:00:00.000-04:00",
          "updated_at": "2026-05-05 12:07:49.396000+00:00",
          "spread": -3.5,
          "home_team": "DET",
          "away_team": "CLE",
          "home_spread": -3.5,
          "away_spread": 3.5,
          "game_spread": -3.5,
          "spread_source": "rotowire",
          "spread_ok": true,
          "spread_reason": "ok",
          "minutes_s": 0.7,
          "p": 0.6817818218178182,
          "p_role": 0.6836816318368163,
          "p_adj": 0.6836816318368163,
          "p_close": 0.6913808619138087,
          "p_close_raw": 0.6892810718928107,
          "p_close_role": 0.6913808619138087,
          "q_blowout": 0.13550088939970018,
          "q_blowout_spread_only": 0.26070104207215794,
          "q_blowout_team_adj": -0.007070125862806323,
          "q_blowout_matchup_adj": -0.11813002680965147,
          "blowout_minute_drop_base": 1.838628601517783,
          "blowout_minute_drop": 1.838628601517783,
          "blowout_rule_minute_drop_mult": 1.0,
          "blowout_rule_sensitivity_mult": 1.0,
          "blowout_rule_count": 0,
          "blowout_rules_applied": "",
          "minutes_s_blowout": 0.5319999999999999,
          "under_blowout_sens_mult": 0.76,
          "under_blowout_sens_eligible": false,
          "minutes_s_close": 0.24499999999999997,
          "is_star": false,
          "rotation_tier": "rotation",
          "blowout_minute_delta": -1.838628601517783,
          "blowout_base_min_for_curve": 20.852245005420652,
          "fragility": 0.011136018511823064,
          "fragility_abs": 0.007699230076992358,
          "fragility_gap_core": 0.007699230076992358,
          "fragility_gap_usage": 0.007699230076992358,
          "fragility_gap_dir": 0.007699230076992358,
          "usage_dep": 0.764478,
          "usage_dep_capped": 0.764478,
          "usage_dep_cap": 1.02,
          "usage_dep_eff": 1.0,
          "usage_risk_gate": 0.0,
          "usage_baseline": 0.78,
          "usage_producer_mult": 0.99,
          "usage_pressure_mult": 0.99,
          "usage_usg_pct": NaN,
          "usage_usg_scaled": 0.0,
          "usage_usg_mult": 1.0,
          "usage_scoring_mult": 1.0,
          "usage_assist_mult": 1.0,
          "usage_rebound_mult": 1.0,
          "usage_threes_mult": 1.0,
          "usage_metric_mult": 1.0,
          "usage_target_rate": 0.07193470053752328,
          "usage_burden_ratio": 0.5255488763667289,
          "usage_dep_raw": 0.764478,
          "p_adj_pre_under_relief": 0.6836816318368163,
          "p_adj_pre_competitive_usage": 0.6836816318368163,
          "competitive_usage_bonus": 0.0,
          "competitive_usage_eligible": false,
          "competitive_usage_usage_gate": 0.0,
          "competitive_usage_frag_gate": 1.0,
          "competitive_usage_tight_gate": 0.44499110600299824,
          "competitive_usage_total_gate": 0.0,
          "competitive_usage_bonus_uncapped": 0.0,
          "competitive_usage_headroom": 0.007699230076992358,
          "under_relief_haircut": 0.0,
          "under_relief_haircut_min": 0.05,
          "under_relief_factor": 1.0,
          "under_relief_applied": false,
          "under_frag": 0.0,
          "under_frag_gap": 0.0,
          "under_frag_gap_usage": 0.0,
          "under_frag_dampen_amount": 0.0,
          "p_adj_pre_under_frag_dampen": 0.6836816318368163,
          "min_mean": 20.852245005420652,
          "min_std": 6.6938243983216,
          "rate_mean": 0.13687537691038107,
          "rate_std": 0.0895289386602282,
          "rate_mean_ctx": 0.13788461187308834,
          "rate_mean_ctx_raw": 0.1378379362595583,
          "rate_std_ctx": 0.10353233534667411,
          "role_metrics_mult": 1.0,
          "crafted_role_workload_enabled": false,
          "role_ctx_mult": 1.0070323777066745,
          "role_ctx_mult_raw": 1.0080747056679413,
          "role_ctx_rate_mult": 1.0073733858162675,
          "role_ctx_rate_mult_raw": 1.0070323777066745,
          "role_ctx_rate_clamp_lo": 0.94,
          "role_ctx_rate_clamp_hi": 1.08,
          "role_ctx_rate_softcap_k": 1.1,
          "role_ctx_sigma_mult": 1.0045710455093384,
          "role_ctx_reason": "ok",
          "role_ctx_damp_applied": "",
          "zero_dnp_mult": 1.0,
          "zero_dnp_debug": "no_zero_dnp_out",
          "recent_form_blend": 0.0,
          "opp_defense_strength": 1.0,
          "form_z_line": 0.7335767709506648,
          "form_series_game": 1.0,
          "form_series_mult": 1.01,
          "form_opp_defense_factor": 0.9946539659807287,
          "form_opp_defense_rel": -0.005346034019271251,
          "form_pace_factor": -0.03364828693424782,
          "form_opp_defense_adj": 0.9946539659807287,
          "form_opp_rate_shift": -0.0007356733561525441,
          "games_used": 10,
          "thin_window_mult": 1.15,
          "is_playoff": false,
          "playoff_rate_applied": "off",
          "playoff_min_applied": "off",
          "role_ctx_outs_used": 1,
          "role_ctx_outs": "[\"Huerter, Kevin\"]",
          "role_ctx_bump": 0.008074705667941329,
          "role_ctx_team": "DET",
          "role_ctx_stat": "REB",
          "role_ctx_min_games": 3.0,
          "role_ctx_by_out": "[{\"out_canon\": \"kevin huerter\", \"weight\": 0.0080747056679413}]",
          "role_metrics_score": 0.0,
          "data_health_flag": "OK",
          "role_ctx_components": "[\"PTS\", \"AST\"]",
          "role_ctx_component_mults": "[1.0094932789186755, 1.0134933682790046]",
          "role_ctx_component_reasons": "[\"ok\", \"ok\"]",
          "p_adj_pre_blowout_bypass": 0.6836816318368163,
          "blowout_bypass_applied": 1,
          "p_adj_pre_shrink": 0.6836816318368163,
          "high_prob_shrink_applied": 0,
          "p_adj_pre_subset_shift": 0.6836816318368163,
          "subset_shift_applied": "under(383)",
          "prob_floor_applied": "goblin_over(47)",
          "logit_shrink_applied": "combo(1556)",
          "p_for_cal": 0.6836816318368163,
          "p_cal_src": "p_adj",
          "p_cal": 0.8055080933316285,
          "p_for_cal_src": "p_adj",
          "p_catboost": 0.8055080933316285,
          "_zero_dnp_flip": false,
          "prop_key": "Daniss Jenkins|REB|OVER|1.5|GOBLIN",
          "external_prior_score": 0.0,
          "external_prior_n": 0,
          "external_prior_sources": "oddsapi",
          "external_prior_epsilon": 0.05,
          "is_questionable": 1,
          "q_out_frac": 0.5,
          "rotowire_game_spread": -3.5,
          "p_cal_marketed": 0.7410674458650983,
          "marketed_score": 0.0
        },
        {
          "player": "Jaylin Williams",
          "tier": "STANDARD",
          "projection_id": "11883993|Jaylin Williams|PA|STANDARD|5.5|OVER",
          "source_projection_id": 11883993,
          "game_id": 156489,
          "game_date": "2026-05-05",
          "home": 1,
          "opp": "LAL",
          "player_key": "jaylin williams",
          "team": "OKC",
          "stat": "PA",
          "stat_raw": "PTS+ASTS",
          "stat_is_canonical": 1,
          "line": 5.5,
          "direction": "OVER",
          "more_allowed": 1,
          "less_allowed": 0,
          "main_line": NaN,
          "alt_line": NaN,
          "is_main": 0,
          "odds_type": "standard",
          "start_time": "2026-05-05T20:30:00.000-04:00",
          "updated_at": "2026-05-05 15:10:13.362000+00:00",
          "spread": -15.5,
          "home_team": "OKC",
          "away_team": "LAL",
          "home_spread": -15.5,
          "away_spread": 15.5,
          "game_spread": -15.5,
          "spread_source": "rotowire",
          "spread_ok": true,
          "spread_reason": "ok",
          "minutes_s": 1.0,
          "p": 0.7901709829017098,
          "p_role": 0.7960703929607039,
          "p_adj": 0.731181104746623,
          "p_close": 0.7921707829217078,
          "p_close_raw": 0.7856714328567144,
          "p_close_role": 0.7921707829217078,
          "q_blowout": 0.6882702956802266,
          "q_blowout_spread_only": 0.5946802993599826,
          "q_blowout_team_adj": 0.0033866897965620616,
          "q_blowout_matchup_adj": 0.09020330652368187,
          "blowout_minute_drop_base": 0.03413554180579936,
          "blowout_minute_drop": 0.026625722608523503,
          "blowout_rule_minute_drop_mult": 0.78,
          "blowout_rule_sensitivity_mult": 0.92,
          "blowout_rule_count": 1,
          "blowout_rules_applied": "combo_scoring_over_high_q_structural_v1",
          "minutes_s_blowout": 0.5888,
          "under_blowout_sens_mult": 0.5888,
          "under_blowout_sens_eligible": false,
          "minutes_s_close": 0.35,
          "is_star": false,
          "rotation_tier": "bench",
          "blowout_minute_delta": -0.03413554180579936,
          "blowout_base_min_for_curve": 14.407626935020712,
          "fragility": 0.0,
          "fragility_abs": 0.0,
          "fragility_gap_core": 0.0,
          "fragility_gap_usage": 0.0,
          "fragility_gap_dir": 0.0,
          "usage_dep": 0.9602999999999999,
          "usage_dep_capped": 0.9602999999999999,
          "usage_dep_cap": 1.06,
          "usage_dep_eff": 0.9602999999999999,
          "usage_risk_gate": 1.0,
          "usage_baseline": 1.0,
          "usage_producer_mult": 0.99,
          "usage_pressure_mult": 0.97,
          "usage_usg_pct": NaN,
          "usage_usg_scaled": 0.0,
          "usage_usg_mult": 1.0,
          "usage_scoring_mult": 1.0,
          "usage_assist_mult": 1.0,
          "usage_rebound_mult": 1.0,
          "usage_threes_mult": 1.0,
          "usage_metric_mult": 1.0,
          "usage_target_rate": 0.23053835969902328,
          "usage_burden_ratio": 0.5602549147747978,
          "usage_dep_raw": 0.9602999999999999,
          "p_adj_pre_under_relief": 0.7960703929607039,
          "p_adj_pre_competitive_usage": 0.7960703929607039,
          "competitive_usage_bonus": 0.0,
          "competitive_usage_eligible": false,
          "competitive_usage_usage_gate": 0.0,
          "competitive_usage_frag_gate": 1.0,
          "competitive_usage_tight_gate": 0.0,
          "competitive_usage_total_gate": 0.0,
          "competitive_usage_bonus_uncapped": 0.0,
          "competitive_usage_headroom": 0.0,
          "under_relief_haircut": 0.0,
          "under_relief_haircut_min": 0.05,
          "under_relief_factor": 1.0,
          "under_relief_applied": false,
          "under_frag": 0.0,
          "under_frag_gap": 0.0,
          "under_frag_gap_usage": 0.0,
          "under_frag_dampen_amount": 0.0,
          "p_adj_pre_under_frag_dampen": 0.7960703929607039,
          "min_mean": 14.407626935020712,
          "min_std": 3.697349479075813,
          "rate_mean": 0.41148833079258457,
          "rate_std": 0.15774295534645652,
          "rate_mean_ctx": 0.41856335092088004,
          "rate_mean_ctx_raw": 0.4187296802654401,
          "rate_std_ctx": 0.20274476218260407,
          "role_metrics_mult": 1.0,
          "crafted_role_workload_enabled": false,
          "role_ctx_mult": 1.017597946116498,
          "role_ctx_mult_raw": 1.021307141681881,
          "role_ctx_rate_mult": 1.0171937321154843,
          "role_ctx_rate_mult_raw": 1.017597946116498,
          "role_ctx_rate_clamp_lo": 0.94,
          "role_ctx_rate_clamp_hi": 1.08,
          "role_ctx_rate_softcap_k": 1.1,
          "role_ctx_sigma_mult": 1.0114386649757237,
          "role_ctx_reason": "ok_combo",
          "role_ctx_damp_applied": "",
          "zero_dnp_mult": 1.6558730435121112,
          "zero_dnp_debug": "zero_dnp:Williams, Jalen(dnp=1,out_min=26,pl_min=14,x1.656,missed=0)",
          "recent_form_blend": 0.0,
          "opp_defense_strength": 1.0,
          "form_z_line": 0.1795325607300696,
          "form_series_game": 1.0,
          "form_series_mult": 1.01,
          "form_opp_defense_factor": 1.003477712844646,
          "form_opp_defense_rel": 0.0034777128446459304,
          "form_pace_factor": -0.0499002576594928,
          "form_opp_defense_adj": 1.003477712844646,
          "form_opp_rate_shift": 0.001426078760994709,
          "games_used": 10,
          "thin_window_mult": 1.15,
          "is_playoff": false,
          "playoff_rate_applied": "off",
          "playoff_min_applied": "off",
          "role_ctx_outs_used": 2,
          "role_ctx_outs": "[\"Sorber, Thomas\", \"Williams, Jalen\"]",
          "role_ctx_bump": 0.021415103547370307,
          "role_ctx_team": "OKC",
          "role_ctx_stat": "PTS",
          "role_ctx_min_games": 3.0,
          "role_ctx_by_out": "[{\"out_canon\": \"jalen williams\", \"weight\": 0.0081210871021337}, {\"out_canon\": \"jalen williams\", \"weight\": 0.0132940164452366}]",
          "role_metrics_score": 0.0,
          "data_health_flag": "OK",
          "role_ctx_components": "[\"PTS\", \"AST\"]",
          "role_ctx_component_mults": "[1.0081210871021336, 1.0132940164452366]",
          "role_ctx_component_reasons": "[\"ok\", \"ok\"]",
          "p_adj_pre_blowout_bypass": 0.7960703929607039,
          "blowout_bypass_applied": 1,
          "p_adj_pre_shrink": 0.7960703929607039,
          "high_prob_shrink_applied": 1,
          "p_adj_pre_subset_shift": 0.7524652130356843,
          "subset_shift_applied": "under(383)",
          "prob_floor_applied": "goblin_over(47)",
          "logit_shrink_applied": "combo(1556)",
          "p_for_cal": 0.731181104746623,
          "p_cal_src": "p_adj",
          "p_cal": 0.7446942198882531,
          "p_for_cal_src": "p_adj",
          "p_catboost": 0.7762248218853903,
          "_zero_dnp_flip": false,
          "prop_key": "Jaylin Williams|PA|OVER|5.5|STANDARD",
          "external_prior_score": 0.0,
          "external_prior_n": 0,
          "external_prior_sources": "",
          "external_prior_epsilon": 0.05,
          "is_questionable": 0,
          "q_out_frac": 0.0,
          "rotowire_game_spread": -15.5,
          "p_cal_marketed": 0.6925656244960754,
          "marketed_score": 0.6925656244960754
        },
        {
          "player": "Quentin Grimes",
          "tier": "STANDARD",
          "projection_id": "11880018|Quentin Grimes|PRA|STANDARD|11.5|OVER",
          "source_projection_id": 11880018,
          "game_id": 156676,
          "game_date": "2026-05-06",
          "home": 0,
          "opp": "NYK",
          "player_key": "quentin grimes",
          "team": "PHI",
          "stat": "PRA",
          "stat_raw": "PTS+REBS+ASTS",
          "stat_is_canonical": 1,
          "line": 11.5,
          "direction": "OVER",
          "more_allowed": 1,
          "less_allowed": 0,
          "main_line": NaN,
          "alt_line": NaN,
          "is_main": 0,
          "odds_type": "standard",
          "start_time": "2026-05-06T19:00:00.000-04:00",
          "updated_at": "2026-05-05 13:25:31.902000+00:00",
          "spread": 0.0,
          "home_team": NaN,
          "away_team": NaN,
          "home_spread": NaN,
          "away_spread": NaN,
          "game_spread": NaN,
          "spread_source": "rotowire",
          "spread_ok": false,
          "spread_reason": "no_game_for_team_date",
          "minutes_s": 1.0,
          "p": 0.5,
          "p_role": 0.5,
          "p_adj": 0.5,
          "p_close": 0.517998200179982,
          "p_close_raw": 0.517998200179982,
          "p_close_role": 0.517998200179982,
          "q_blowout": 0.24063194727365875,
          "q_blowout_spread_only": 0.23727785186827832,
          "q_blowout_team_adj": 0.0033540954053804238,
          "q_blowout_matchup_adj": 0.0,
          "blowout_minute_drop_base": 2.448000922021354,
          "blowout_minute_drop": 2.448000922021354,
          "blowout_rule_minute_drop_mult": 1.0,
          "blowout_rule_sensitivity_mult": 1.0,
          "blowout_rule_count": 0,
          "blowout_rules_applied": "",
          "minutes_s_blowout": 0.76,
          "under_blowout_sens_mult": 0.76,
          "under_blowout_sens_eligible": false,
          "minutes_s_close": 0.35,
          "is_star": false,
          "rotation_tier": "rotation",
          "blowout_minute_delta": -2.448000922021354,
          "blowout_base_min_for_curve": 23.02857472150483,
          "fragility": 0.034551429500485155,
          "fragility_abs": 0.017897578294896844,
          "fragility_gap_core": 0.017998200179981994,
          "fragility_gap_usage": 0.017897578294896844,
          "fragility_gap_dir": 0.017897578294896844,
          "usage_dep": 0.99,
          "usage_dep_capped": 0.99,
          "usage_dep_cap": 1.06,
          "usage_dep_eff": 0.9944093362625746,
          "usage_risk_gate": 0.5590663737425485,
          "usage_baseline": 1.0,
          "usage_producer_mult": 0.99,
          "usage_pressure_mult": 1.0,
          "usage_usg_pct": NaN,
          "usage_usg_scaled": 0.0,
          "usage_usg_mult": 1.0,
          "usage_scoring_mult": 1.0,
          "usage_assist_mult": 1.0,
          "usage_rebound_mult": 1.0,
          "usage_threes_mult": 1.0,
          "usage_metric_mult": 1.0,
          "usage_target_rate": 0.4993795811974818,
          "usage_burden_ratio": 0.966593497571302,
          "usage_dep_raw": 0.99,
          "p_adj_pre_under_relief": 0.5,
          "p_adj_pre_competitive_usage": 0.5,
          "competitive_usage_bonus": 0.0,
          "competitive_usage_eligible": true,
          "competitive_usage_usage_gate": 0.0,
          "competitive_usage_frag_gate": 1.0,
          "competitive_usage_tight_gate": 0.0,
          "competitive_usage_total_gate": 0.0,
          "competitive_usage_bonus_uncapped": 0.0,
          "competitive_usage_headroom": 0.017998200179981994,
          "under_relief_haircut": 0.0,
          "under_relief_haircut_min": 0.05,
          "under_relief_factor": 1.0,
          "under_relief_applied": false,
          "under_frag": 0.0,
          "under_frag_gap": 0.0,
          "under_frag_gap_usage": 0.0,
          "under_frag_dampen_amount": 0.0,
          "p_adj_pre_under_frag_dampen": 0.5,
          "min_mean": 23.02857472150483,
          "min_std": 2.4094198528530364,
          "rate_mean": 0.5166386722569944,
          "rate_std": 0.14586586784083116,
          "rate_mean_ctx": 0.5166386722569944,
          "rate_mean_ctx_raw": 0.5166386722569944,
          "rate_std_ctx": 0.1853590515587362,
          "role_metrics_mult": 1.0,
          "crafted_role_workload_enabled": false,
          "role_ctx_mult": 1.0,
          "role_ctx_mult_raw": 1.0,
          "role_ctx_rate_mult": 1.0,
          "role_ctx_rate_mult_raw": 1.0,
          "role_ctx_rate_clamp_lo": 0.94,
          "role_ctx_rate_clamp_hi": 1.08,
          "role_ctx_rate_softcap_k": 1.1,
          "role_ctx_sigma_mult": 1.0,
          "role_ctx_reason": "no_outs",
          "role_ctx_damp_applied": "",
          "zero_dnp_mult": 1.0,
          "zero_dnp_debug": "no_outs_or_gl",
          "recent_form_blend": 0.0,
          "opp_defense_strength": 1.0,
          "form_z_line": 0.11832165615567966,
          "form_series_game": 1.0,
          "form_series_mult": 1.01,
          "form_opp_defense_factor": 1.0,
          "form_opp_defense_rel": 0.0,
          "form_pace_factor": 0.0,
          "form_opp_defense_adj": 1.0,
          "form_opp_rate_shift": 0.0,
          "games_used": 10,
          "thin_window_mult": 1.15,
          "is_playoff": false,
          "playoff_rate_applied": "off",
          "playoff_min_applied": "off",
          "role_ctx_outs_used": 0,
          "role_ctx_outs": "[]",
          "role_ctx_bump": 0.0,
          "role_ctx_team": NaN,
          "role_ctx_stat": NaN,
          "role_ctx_min_games": NaN,
          "role_ctx_by_out": "[]",
          "role_metrics_score": 0.0,
          "data_health_flag": "OK",
          "role_ctx_components": "[\"PTS\", \"REB\", \"AST\"]",
          "role_ctx_component_mults": "[1.0, 1.0, 1.0]",
          "role_ctx_component_reasons": "[\"no_outs\", \"no_outs\", \"no_outs\"]",
          "p_adj_pre_blowout_bypass": 0.5,
          "blowout_bypass_applied": 0,
          "p_adj_pre_shrink": 0.5,
          "high_prob_shrink_applied": 0,
          "p_adj_pre_subset_shift": 0.5,
          "subset_shift_applied": "under(383)",
          "prob_floor_applied": "goblin_over(47)",
          "logit_shrink_applied": "combo(1556)",
          "p_for_cal": 0.5,
          "p_cal_src": "p_adj",
          "p_cal": 0.7976300141879747,
          "p_for_cal_src": "p_adj",
          "p_catboost": 0.7976300141879747,
          "_zero_dnp_flip": false,
          "prop_key": "Quentin Grimes|PRA|OVER|11.5|STANDARD",
          "external_prior_score": 0.0,
          "external_prior_n": 0,
          "external_prior_sources": "oddsapi",
          "external_prior_epsilon": 0.05,
          "is_questionable": 0,
          "q_out_frac": 0.0,
          "rotowire_game_spread": NaN,
          "p_cal_marketed": 0.6859618122016583,
          "marketed_score": 0.6859618122016583
        }
      ],
      "hit_prob": 0.3241260378563384,
      "hit_prob_raw": 0.24370378786190858,
      "payout_mult": 1.8973665961010275,
      "ev": 0.6149859171551936,
      "n_legs": 4,
      "high_confidence": true
    },
    {
      "label": "3-leg",
      "legs": [
        {
          "player": "De'Aaron Fox",
          "tier": "GOBLIN",
          "projection_id": "11881344|De'Aaron Fox|PTS|GOBLIN|14.5|OVER",
          "source_projection_id": 11881344,
          "game_id": 156550,
          "game_date": "2026-05-06",
          "home": 1,
          "opp": "MIN",
          "player_key": "de aaron fox",
          "team": "SAS",
          "stat": "PTS",
          "stat_raw": "POINTS",
          "stat_is_canonical": 1,
          "line": 14.5,
          "direction": "OVER",
          "more_allowed": 1,
          "less_allowed": 0,
          "main_line": NaN,
          "alt_line": NaN,
          "is_main": 0,
          "odds_type": "goblin",
          "start_time": "2026-05-06T21:30:00.000-04:00",
          "updated_at": "2026-05-05 07:30:36.878000+00:00",
          "spread": 0.0,
          "home_team": NaN,
          "away_team": NaN,
          "home_spread": NaN,
          "away_spread": NaN,
          "game_spread": NaN,
          "spread_source": "rotowire",
          "spread_ok": false,
          "spread_reason": "no_game_for_team_date",
          "minutes_s": 1.0,
          "p": 0.6355864413558644,
          "p_role": 0.6355864413558644,
          "p_adj": 0.6837878203596552,
          "p_close": 0.6678832116788321,
          "p_close_raw": 0.6678832116788321,
          "p_close_role": 0.6678832116788321,
          "q_blowout": 0.23155582495745836,
          "q_blowout_spread_only": 0.23727785186827832,
          "q_blowout_team_adj": -0.005722026910819967,
          "q_blowout_matchup_adj": 0.0,
          "blowout_minute_drop_base": 5.27081369973302,
          "blowout_minute_drop": 5.27081369973302,
          "blowout_rule_minute_drop_mult": 1.0,
          "blowout_rule_sensitivity_mult": 1.0,
          "blowout_rule_count": 0,
          "blowout_rules_applied": "",
          "minutes_s_blowout": 0.76,
          "under_blowout_sens_mult": 0.76,
          "under_blowout_sens_eligible": false,
          "minutes_s_close": 0.35,
          "is_star": true,
          "rotation_tier": "star",
          "blowout_minute_delta": -5.27081369973302,
          "blowout_base_min_for_curve": 33.110048927617925,
          "fragility": 0.04738043474726824,
          "fragility_abs": 0.03164459692974485,
          "fragility_gap_core": 0.03229677032296774,
          "fragility_gap_usage": 0.03164459692974485,
          "fragility_gap_dir": 0.03164459692974485,
          "usage_dep": 0.9602999999999999,
          "usage_dep_capped": 0.9602999999999999,
          "usage_dep_cap": 1.06,
          "usage_dep_eff": 0.9798068541621605,
          "usage_risk_gate": 0.5086434719858797,
          "usage_baseline": 1.0,
          "usage_producer_mult": 0.99,
          "usage_pressure_mult": 0.97,
          "usage_usg_pct": NaN,
          "usage_usg_scaled": 0.0,
          "usage_usg_mult": 1.0,
          "usage_scoring_mult": 1.0,
          "usage_assist_mult": 1.0,
          "usage_rebound_mult": 1.0,
          "usage_threes_mult": 1.0,
          "usage_metric_mult": 1.0,
          "usage_target_rate": 0.43793351171719913,
          "usage_burden_ratio": 0.8160443920866178,
          "usage_dep_raw": 0.9602999999999999,
          "p_adj_pre_under_relief": 0.6355864413558644,
          "p_adj_pre_competitive_usage": 0.6355864413558644,
          "competitive_usage_bonus": 0.0,
          "competitive_usage_eligible": true,
          "competitive_usage_usage_gate": 0.0,
          "competitive_usage_frag_gate": 0.907744565659147,
          "competitive_usage_tight_gate": 0.0,
          "competitive_usage_total_gate": 0.0,
          "competitive_usage_bonus_uncapped": 0.0,
          "competitive_usage_headroom": 0.03229677032296774,
          "under_relief_haircut": 0.0,
          "under_relief_haircut_min": 0.05,
          "under_relief_factor": 1.0,
          "under_relief_applied": false,
          "under_frag": 0.0,
          "under_frag_gap": 0.0,
          "under_frag_gap_usage": 0.0,
          "under_frag_dampen_amount": 0.0,
          "p_adj_pre_under_frag_dampen": 0.6355864413558644,
          "min_mean": 33.110048927617925,
          "min_std": 3.767099960157638,
          "rate_mean": 0.5366540300551631,
          "rate_std": 0.1239985752484214,
          "rate_mean_ctx": 0.5366540300551631,
          "rate_mean_ctx_raw": 0.5366540300551631,
          "rate_std_ctx": 0.18537786999638997,
          "role_metrics_mult": 1.0,
          "crafted_role_workload_enabled": false,
          "role_ctx_mult": 1.0,
          "role_ctx_mult_raw": 1.0,
          "role_ctx_rate_mult": 1.0,
          "role_ctx_rate_mult_raw": 1.0,
          "role_ctx_rate_clamp_lo": 0.94,
          "role_ctx_rate_clamp_hi": 1.08,
          "role_ctx_rate_softcap_k": 1.1,
          "role_ctx_sigma_mult": 1.0,
          "role_ctx_reason": "no_outs",
          "role_ctx_damp_applied": "star_ben(33m,x0.4)",
          "zero_dnp_mult": 1.0,
          "zero_dnp_debug": "no_outs_or_gl",
          "recent_form_blend": 0.0,
          "opp_defense_strength": 1.0,
          "form_z_line": 0.8266717863498861,
          "form_series_game": 1.0,
          "form_series_mult": 1.01,
          "form_opp_defense_factor": 0.9929953224756939,
          "form_opp_defense_rel": -0.007004677524306113,
          "form_pace_factor": 0.0,
          "form_opp_defense_adj": 0.9929953224756939,
          "form_opp_rate_shift": -0.0037856053674892864,
          "games_used": 10,
          "thin_window_mult": 1.15,
          "is_playoff": false,
          "playoff_rate_applied": "off",
          "playoff_min_applied": "off",
          "role_ctx_outs_used": 0,
          "role_ctx_outs": "[]",
          "role_ctx_bump": 0.0,
          "role_ctx_team": NaN,
          "role_ctx_stat": NaN,
          "role_ctx_min_games": NaN,
          "role_ctx_by_out": "[]",
          "role_metrics_score": 0.0,
          "data_health_flag": "OK",
          "role_ctx_components": "[\"PTS\"]",
          "role_ctx_component_mults": "[1.0]",
          "role_ctx_component_reasons": "[\"no_outs\"]",
          "p_adj_pre_blowout_bypass": 0.6355864413558644,
          "blowout_bypass_applied": 0,
          "p_adj_pre_shrink": 0.6355864413558644,
          "high_prob_shrink_applied": 0,
          "p_adj_pre_subset_shift": 0.6355864413558644,
          "subset_shift_applied": "under(383)",
          "prob_floor_applied": "goblin_over(47)",
          "logit_shrink_applied": "combo(1556)",
          "p_for_cal": 0.6355864413558644,
          "p_cal_src": "p_adj",
          "p_cal": 0.7526776180790121,
          "p_for_cal_src": "p_adj",
          "p_catboost": 0.7526776180790121,
          "_zero_dnp_flip": false,
          "prop_key": "De'Aaron Fox|PTS|OVER|14.5|GOBLIN",
          "external_prior_score": 0.9640275800758169,
          "external_prior_n": 1,
          "external_prior_sources": "oddsapi",
          "external_prior_epsilon": 0.05,
          "is_questionable": 0,
          "q_out_frac": 0.0,
          "rotowire_game_spread": NaN,
          "p_cal_marketed": 0.7376240657174319,
          "marketed_score": 0.0
        },
        {
          "player": "Julian Champagnie",
          "tier": "STANDARD",
          "projection_id": "11881458|Julian Champagnie|PTS|STANDARD|8.5|OVER",
          "source_projection_id": 11881458,
          "game_id": 156550,
          "game_date": "2026-05-06",
          "home": 1,
          "opp": "MIN",
          "player_key": "julian champagnie",
          "team": "SAS",
          "stat": "PTS",
          "stat_raw": "POINTS",
          "stat_is_canonical": 1,
          "line": 8.5,
          "direction": "OVER",
          "more_allowed": 1,
          "less_allowed": 0,
          "main_line": NaN,
          "alt_line": NaN,
          "is_main": 0,
          "odds_type": "standard",
          "start_time": "2026-05-06T21:30:00.000-04:00",
          "updated_at": "2026-05-05 04:27:26.651000+00:00",
          "spread": 0.0,
          "home_team": NaN,
          "away_team": NaN,
          "home_spread": NaN,
          "away_spread": NaN,
          "game_spread": NaN,
          "spread_source": "rotowire",
          "spread_ok": false,
          "spread_reason": "no_game_for_team_date",
          "minutes_s": 1.0,
          "p": 0.6127887211278872,
          "p_role": 0.6127887211278872,
          "p_adj": 0.6127887211278872,
          "p_close": 0.6282871712828717,
          "p_close_raw": 0.6282871712828717,
          "p_close_role": 0.6282871712828717,
          "q_blowout": 0.23155582495745836,
          "q_blowout_spread_only": 0.23727785186827832,
          "q_blowout_team_adj": -0.005722026910819967,
          "q_blowout_matchup_adj": 0.0,
          "blowout_minute_drop_base": 3.803885244856727,
          "blowout_minute_drop": 3.803885244856727,
          "blowout_rule_minute_drop_mult": 1.0,
          "blowout_rule_sensitivity_mult": 1.0,
          "blowout_rule_count": 0,
          "blowout_rules_applied": "",
          "minutes_s_blowout": 0.76,
          "under_blowout_sens_mult": 0.76,
          "under_blowout_sens_eligible": false,
          "minutes_s_close": 0.35,
          "is_star": false,
          "rotation_tier": "starter",
          "blowout_minute_delta": -3.803885244856727,
          "blowout_base_min_for_curve": 27.871018731631164,
          "fragility": 0.024169660602392787,
          "fragility_abs": 0.015185487690744433,
          "fragility_gap_core": 0.015498450154984522,
          "fragility_gap_usage": 0.015185487690744433,
          "fragility_gap_dir": 0.015185487690744433,
          "usage_dep": 0.9602999999999999,
          "usage_dep_capped": 0.9602999999999999,
          "usage_dep_cap": 1.06,
          "usage_dep_eff": 0.9798068541621605,
          "usage_risk_gate": 0.5086434719858797,
          "usage_baseline": 1.0,
          "usage_producer_mult": 0.99,
          "usage_pressure_mult": 0.97,
          "usage_usg_pct": NaN,
          "usage_usg_scaled": 0.0,
          "usage_usg_mult": 1.0,
          "usage_scoring_mult": 1.0,
          "usage_assist_mult": 1.0,
          "usage_rebound_mult": 1.0,
          "usage_threes_mult": 1.0,
          "usage_metric_mult": 1.0,
          "usage_target_rate": 0.3049762939003462,
          "usage_burden_ratio": 0.7743503671069804,
          "usage_dep_raw": 0.9602999999999999,
          "p_adj_pre_under_relief": 0.6127887211278872,
          "p_adj_pre_competitive_usage": 0.6127887211278872,
          "competitive_usage_bonus": 0.0,
          "competitive_usage_eligible": true,
          "competitive_usage_usage_gate": 0.0,
          "competitive_usage_frag_gate": 1.0,
          "competitive_usage_tight_gate": 0.0,
          "competitive_usage_total_gate": 0.0,
          "competitive_usage_bonus_uncapped": 0.0,
          "competitive_usage_headroom": 0.015498450154984522,
          "under_relief_haircut": 0.0,
          "under_relief_haircut_min": 0.05,
          "under_relief_factor": 1.0,
          "under_relief_applied": false,
          "under_frag": 0.0,
          "under_frag_gap": 0.0,
          "under_frag_gap_usage": 0.0,
          "under_frag_dampen_amount": 0.0,
          "p_adj_pre_under_frag_dampen": 0.6127887211278872,
          "min_mean": 27.871018731631164,
          "min_std": 3.1024404244760335,
          "rate_mean": 0.39384793609610597,
          "rate_std": 0.15799867785641822,
          "rate_mean_ctx": 0.39384793609610597,
          "rate_mean_ctx_raw": 0.39384793609610597,
          "rate_std_ctx": 0.23620802339534522,
          "role_metrics_mult": 1.0,
          "crafted_role_workload_enabled": false,
          "role_ctx_mult": 1.0,
          "role_ctx_mult_raw": 1.0,
          "role_ctx_rate_mult": 1.0,
          "role_ctx_rate_mult_raw": 1.0,
          "role_ctx_rate_clamp_lo": 0.94,
          "role_ctx_rate_clamp_hi": 1.08,
          "role_ctx_rate_softcap_k": 1.1,
          "role_ctx_sigma_mult": 1.0,
          "role_ctx_reason": "no_outs",
          "role_ctx_damp_applied": "",
          "zero_dnp_mult": 1.0,
          "zero_dnp_debug": "no_outs_or_gl",
          "recent_form_blend": 0.0,
          "opp_defense_strength": 1.0,
          "form_z_line": 0.5800673897375538,
          "form_series_game": 1.0,
          "form_series_mult": 1.01,
          "form_opp_defense_factor": 0.9929953224756939,
          "form_opp_defense_rel": -0.007004677524306113,
          "form_pace_factor": 0.0,
          "form_opp_defense_adj": 0.9929953224756939,
          "form_opp_rate_shift": -0.00277823845039743,
          "games_used": 10,
          "thin_window_mult": 1.15,
          "is_playoff": false,
          "playoff_rate_applied": "off",
          "playoff_min_applied": "off",
          "role_ctx_outs_used": 0,
          "role_ctx_outs": "[]",
          "role_ctx_bump": 0.0,
          "role_ctx_team": NaN,
          "role_ctx_stat": NaN,
          "role_ctx_min_games": NaN,
          "role_ctx_by_out": "[]",
          "role_metrics_score": 0.0,
          "data_health_flag": "OK",
          "role_ctx_components": "[\"PTS\"]",
          "role_ctx_component_mults": "[1.0]",
          "role_ctx_component_reasons": "[\"no_outs\"]",
          "p_adj_pre_blowout_bypass": 0.6127887211278872,
          "blowout_bypass_applied": 0,
          "p_adj_pre_shrink": 0.6127887211278872,
          "high_prob_shrink_applied": 0,
          "p_adj_pre_subset_shift": 0.6127887211278872,
          "subset_shift_applied": "under(383)",
          "prob_floor_applied": "goblin_over(47)",
          "logit_shrink_applied": "combo(1556)",
          "p_for_cal": 0.6127887211278872,
          "p_cal_src": "p_adj",
          "p_cal": 0.7223755124680252,
          "p_for_cal_src": "p_adj",
          "p_catboost": 0.7223755124680252,
          "_zero_dnp_flip": false,
          "prop_key": "Julian Champagnie|PTS|OVER|8.5|STANDARD",
          "external_prior_score": 0.0,
          "external_prior_n": 0,
          "external_prior_sources": "oddsapi",
          "external_prior_epsilon": 0.05,
          "is_questionable": 0,
          "q_out_frac": 0.0,
          "rotowire_game_spread": NaN,
          "p_cal_marketed": 0.6790329817199436,
          "marketed_score": 0.6790329817199436
        },
        {
          "player": "Max Strus",
          "tier": "STANDARD",
          "projection_id": "11862132|Max Strus|PTS|STANDARD|8.5|OVER",
          "source_projection_id": 11862132,
          "game_id": 156892,
          "game_date": "2026-05-05",
          "home": 0,
          "opp": "DET",
          "player_key": "max strus",
          "team": "CLE",
          "stat": "PTS",
          "stat_raw": "POINTS",
          "stat_is_canonical": 1,
          "line": 8.5,
          "direction": "OVER",
          "more_allowed": 1,
          "less_allowed": 0,
          "main_line": NaN,
          "alt_line": NaN,
          "is_main": 0,
          "odds_type": "standard",
          "start_time": "2026-05-05T19:00:00.000-04:00",
          "updated_at": "2026-05-05 12:07:56.678000+00:00",
          "spread": 3.5,
          "home_team": "DET",
          "away_team": "CLE",
          "home_spread": -3.5,
          "away_spread": 3.5,
          "game_spread": 3.5,
          "spread_source": "rotowire",
          "spread_ok": true,
          "spread_reason": "ok",
          "minutes_s": 1.0,
          "p": 0.48780121987801217,
          "p_role": 0.48780121987801217,
          "p_adj": 0.4878012198780122,
          "p_close": 0.4864013598640136,
          "p_close_raw": 0.4864013598640136,
          "p_close_role": 0.4864013598640136,
          "q_blowout": 0.13550088939970018,
          "q_blowout_spread_only": 0.26070104207215794,
          "q_blowout_team_adj": -0.007070125862806323,
          "q_blowout_matchup_adj": -0.11813002680965147,
          "blowout_minute_drop_base": 3.3639468023003234,
          "blowout_minute_drop": 3.3639468023003234,
          "blowout_rule_minute_drop_mult": 1.0,
          "blowout_rule_sensitivity_mult": 1.0,
          "blowout_rule_count": 0,
          "blowout_rules_applied": "",
          "minutes_s_blowout": 0.76,
          "under_blowout_sens_mult": 0.76,
          "under_blowout_sens_eligible": false,
          "minutes_s_close": 0.35,
          "is_star": false,
          "rotation_tier": "starter",
          "blowout_minute_delta": -3.3639468023003234,
          "blowout_base_min_for_curve": 26.299810008215438,
          "fragility": 0.0,
          "fragility_abs": 0.0,
          "fragility_gap_core": 0.0,
          "fragility_gap_usage": 0.0,
          "fragility_gap_dir": 0.0,
          "usage_dep": 1.0296,
          "usage_dep_capped": 1.0296,
          "usage_dep_cap": 1.06,
          "usage_dep_eff": 1.0,
          "usage_risk_gate": 0.0,
          "usage_baseline": 1.0,
          "usage_producer_mult": 0.99,
          "usage_pressure_mult": 1.04,
          "usage_usg_pct": NaN,
          "usage_usg_scaled": 0.0,
          "usage_usg_mult": 1.0,
          "usage_scoring_mult": 1.0,
          "usage_assist_mult": 1.0,
          "usage_rebound_mult": 1.0,
          "usage_threes_mult": 1.0,
          "usage_metric_mult": 1.0,
          "usage_target_rate": 0.32319625112671163,
          "usage_burden_ratio": 0.9993235370576963,
          "usage_dep_raw": 1.0296,
          "p_adj_pre_under_relief": 0.48780121987801217,
          "p_adj_pre_competitive_usage": 0.48780121987801217,
          "competitive_usage_bonus": 0.0,
          "competitive_usage_eligible": false,
          "competitive_usage_usage_gate": 0.0,
          "competitive_usage_frag_gate": 1.0,
          "competitive_usage_tight_gate": 0.44499110600299824,
          "competitive_usage_total_gate": 0.0,
          "competitive_usage_bonus_uncapped": 0.0,
          "competitive_usage_headroom": 0.0,
          "under_relief_haircut": 0.0,
          "under_relief_haircut_min": 0.05,
          "under_relief_factor": 1.0,
          "under_relief_applied": false,
          "under_frag": 0.0,
          "under_frag_gap": 0.0,
          "under_frag_gap_usage": 0.0,
          "under_frag_dampen_amount": 0.0,
          "p_adj_pre_under_frag_dampen": 0.48780121987801217,
          "min_mean": 26.299810008215438,
          "min_std": 3.075550709200515,
          "rate_mean": 0.32341502940909095,
          "rate_std": 0.23106164463208123,
          "rate_mean_ctx": 0.32341502940909095,
          "rate_mean_ctx_raw": 0.32341502940909095,
          "rate_std_ctx": 0.3454371587249614,
          "role_metrics_mult": 1.0,
          "crafted_role_workload_enabled": false,
          "role_ctx_mult": 1.0,
          "role_ctx_mult_raw": 1.0,
          "role_ctx_rate_mult": 1.0,
          "role_ctx_rate_mult_raw": 1.0,
          "role_ctx_rate_clamp_lo": 0.94,
          "role_ctx_rate_clamp_hi": 1.08,
          "role_ctx_rate_softcap_k": 1.1,
          "role_ctx_sigma_mult": 1.0,
          "role_ctx_reason": "no_outs",
          "role_ctx_damp_applied": "",
          "zero_dnp_mult": 1.0,
          "zero_dnp_debug": "no_outs_or_gl",
          "recent_form_blend": 0.0,
          "opp_defense_strength": 1.0,
          "form_z_line": 0.10519951278270166,
          "form_series_game": 1.0,
          "form_series_mult": 1.01,
          "form_opp_defense_factor": 0.9306804917753801,
          "form_opp_defense_rel": -0.06931950822461985,
          "form_pace_factor": -0.03364828693424782,
          "form_opp_defense_adj": 0.9306804917753801,
          "form_opp_rate_shift": -0.024088794155685378,
          "games_used": 10,
          "thin_window_mult": 1.15,
          "is_playoff": false,
          "playoff_rate_applied": "off",
          "playoff_min_applied": "off",
          "role_ctx_outs_used": 0,
          "role_ctx_outs": "[]",
          "role_ctx_bump": 0.0,
          "role_ctx_team": NaN,
          "role_ctx_stat": NaN,
          "role_ctx_min_games": NaN,
          "role_ctx_by_out": "[]",
          "role_metrics_score": 0.0,
          "data_health_flag": "OK",
          "role_ctx_components": "[\"PTS\"]",
          "role_ctx_component_mults": "[1.0]",
          "role_ctx_component_reasons": "[\"no_outs\"]",
          "p_adj_pre_blowout_bypass": 0.48780121987801217,
          "blowout_bypass_applied": 1,
          "p_adj_pre_shrink": 0.48780121987801217,
          "high_prob_shrink_applied": 0,
          "p_adj_pre_subset_shift": 0.48780121987801217,
          "subset_shift_applied": "under(383)",
          "prob_floor_applied": "goblin_over(47)",
          "logit_shrink_applied": "combo(1556)",
          "p_for_cal": 0.4878012198780122,
          "p_cal_src": "p_adj",
          "p_cal": 0.7099391532037136,
          "p_for_cal_src": "p_adj",
          "p_catboost": 0.7099391532037136,
          "_zero_dnp_flip": false,
          "prop_key": "Max Strus|PTS|OVER|8.5|STANDARD",
          "external_prior_score": 0.0,
          "external_prior_n": 0,
          "external_prior_sources": "oddsapi",
          "external_prior_epsilon": 0.05,
          "is_questionable": 0,
          "q_out_frac": 0.0,
          "rotowire_game_spread": 3.5,
          "p_cal_marketed": 0.6673428040114907,
          "marketed_score": 0.6673428040114907
        }
      ],
      "hit_prob": 0.5306268352420856,
      "hit_prob_raw": 0.3177406199054405,
      "payout_mult": 1.9309787692112594,
      "ev": 1.0246291532262284,
      "n_legs": 3,
      "high_confidence": true
    }
  ],
  "meta": {
    "builder": "marketed_slip_builder",
    "correlation_adjusted": true,
    "stat_calibrated": true,
    "templates": [
      "3-leg: 1G+2S",
      "4-leg: 2G+2S",
      "5-leg: 2G+2S+1D"
    ]
  }
}