{
  "manifest_type": "catboost_playoff_lodo_v3",
  "created_at": "2026-05-09 22:09:46",
  "verdict": "REJECT (per-slate regression)",
  "summary": {
    "n_dates": 9,
    "n_legs_total": 13186,
    "oof_brier_baseline": 0.232166,
    "oof_brier_v3": 0.227946,
    "oof_brier_delta_mB": -4.22,
    "worst_slate_mB": 10.77,
    "per_slate_gate_mB_large": 5.0,
    "per_slate_gate_mB_small": 10.0,
    "small_slate_threshold": 1000
  },
  "config": {
    "cache": "_v1_playoff_resim_cache.pkl",
    "mode": "residual",
    "residual_clip": 0.2,
    "residual_scale": 0.4,
    "features": [
      "p_for_cal",
      "z_line",
      "min_cv",
      "is_combo",
      "bp_score_gated",
      "bp_has",
      "is_assists",
      "is_threes",
      "thin_flag",
      "line_norm",
      "is_home_feat",
      "min_sensitivity",
      "game_total_norm",
      "is_b2b",
      "margin",
      "stat_cat",
      "tier_cat",
      "line_dist",
      "tail_risk",
      "line_tightness",
      "margin_x_under",
      "q_blowout",
      "rate_cv",
      "q_x_under"
    ],
    "cat_features": [
      "stat_cat",
      "tier_cat"
    ],
    "hyperparams": {
      "iterations": 1500,
      "depth": 5,
      "learning_rate": 0.02,
      "l2_leaf_reg": 6.0,
      "min_data_in_leaf": 50,
      "loss_function": "RMSE",
      "eval_metric": "RMSE",
      "random_seed": 42,
      "verbose": 100,
      "early_stopping_rounds": 75,
      "use_best_model": true
    }
  },
  "fold_results": [
    {
      "date": "2026-04-30",
      "n_test": 1942,
      "n_train": 11244,
      "best_iter": 1499,
      "brier_before": 0.322414,
      "brier_after": 0.296062,
      "delta": -0.026352,
      "delta_mb": -26.35,
      "resid_mean": 0.0731,
      "resid_abs": 0.126,
      "model_path": "C:\\Users\\13142\\Atlas\\Atlas\\data\\model\\catboost_playoff_v3\\catboost_v3_fold_2026-04-30.cbm"
    },
    {
      "date": "2026-05-01",
      "n_test": 1938,
      "n_train": 11248,
      "best_iter": 1499,
      "brier_before": 0.212415,
      "brier_after": 0.21563,
      "delta": 0.003216,
      "delta_mb": 3.22,
      "resid_mean": 0.009,
      "resid_abs": 0.0967,
      "model_path": "C:\\Users\\13142\\Atlas\\Atlas\\data\\model\\catboost_playoff_v3\\catboost_v3_fold_2026-05-01.cbm"
    },
    {
      "date": "2026-05-02",
      "n_test": 628,
      "n_train": 12558,
      "best_iter": 1499,
      "brier_before": 0.278783,
      "brier_after": 0.289557,
      "delta": 0.010773,
      "delta_mb": 10.77,
      "resid_mean": -0.0358,
      "resid_abs": 0.1101,
      "model_path": "C:\\Users\\13142\\Atlas\\Atlas\\data\\model\\catboost_playoff_v3\\catboost_v3_fold_2026-05-02.cbm"
    },
    {
      "date": "2026-05-03",
      "n_test": 1323,
      "n_train": 11863,
      "best_iter": 1499,
      "brier_before": 0.22703,
      "brier_after": 0.22759,
      "delta": 0.00056,
      "delta_mb": 0.56,
      "resid_mean": 0.0108,
      "resid_abs": 0.103,
      "model_path": "C:\\Users\\13142\\Atlas\\Atlas\\data\\model\\catboost_playoff_v3\\catboost_v3_fold_2026-05-03.cbm"
    },
    {
      "date": "2026-05-04",
      "n_test": 1371,
      "n_train": 11815,
      "best_iter": 1499,
      "brier_before": 0.211886,
      "brier_after": 0.217415,
      "delta": 0.005529,
      "delta_mb": 5.53,
      "resid_mean": 0.0234,
      "resid_abs": 0.106,
      "model_path": "C:\\Users\\13142\\Atlas\\Atlas\\data\\model\\catboost_playoff_v3\\catboost_v3_fold_2026-05-04.cbm"
    },
    {
      "date": "2026-05-05",
      "n_test": 1523,
      "n_train": 11663,
      "best_iter": 1499,
      "brier_before": 0.202337,
      "brier_after": 0.197693,
      "delta": -0.004645,
      "delta_mb": -4.64,
      "resid_mean": -0.0375,
      "resid_abs": 0.112,
      "model_path": "C:\\Users\\13142\\Atlas\\Atlas\\data\\model\\catboost_playoff_v3\\catboost_v3_fold_2026-05-05.cbm"
    },
    {
      "date": "2026-05-06",
      "n_test": 1434,
      "n_train": 11752,
      "best_iter": 1499,
      "brier_before": 0.203541,
      "brier_after": 0.200144,
      "delta": -0.003396,
      "delta_mb": -3.4,
      "resid_mean": -0.0151,
      "resid_abs": 0.0979,
      "model_path": "C:\\Users\\13142\\Atlas\\Atlas\\data\\model\\catboost_playoff_v3\\catboost_v3_fold_2026-05-06.cbm"
    },
    {
      "date": "2026-05-07",
      "n_test": 1562,
      "n_train": 11624,
      "best_iter": 1499,
      "brier_before": 0.208821,
      "brier_after": 0.204474,
      "delta": -0.004347,
      "delta_mb": -4.35,
      "resid_mean": -0.0048,
      "resid_abs": 0.1152,
      "model_path": "C:\\Users\\13142\\Atlas\\Atlas\\data\\model\\catboost_playoff_v3\\catboost_v3_fold_2026-05-07.cbm"
    },
    {
      "date": "2026-05-08",
      "n_test": 1465,
      "n_train": 11721,
      "best_iter": 1499,
      "brier_before": 0.226216,
      "brier_after": 0.221396,
      "delta": -0.00482,
      "delta_mb": -4.82,
      "resid_mean": -0.02,
      "resid_abs": 0.1037,
      "model_path": "C:\\Users\\13142\\Atlas\\Atlas\\data\\model\\catboost_playoff_v3\\catboost_v3_fold_2026-05-08.cbm"
    }
  ]
}